{
  "season_id": "kn54qllh2zoqvy9",
  "brackets": [
    {
      "id": "965mkyh7xvgr1ge",
      "competition_id": "l965mkyhn0r1ge4",
      "season_id": "kn54qllh2zoqvy9",
      "name": "Knockout stage",
      "abbr": "Knockout Stage",
      "start_time": 1248969600,
      "end_time": 1274111940,
      "rounds": [
        {
          "id": "1l4rjnhkx6gm7vx",
          "bracket_id": "965mkyh7xvgr1ge",
          "name": "Round1",
          "abbr": "R1",
          "start_time": 1249065000,
          "end_time": 1249324200,
          "number": 1,
          "match_ups": [
            {
              "id": "dn1m1gh4ndp1moe",
              "round_id": "1l4rjnhkx6gm7vx",
              "number": 1,
              "type_id": 1,
              "state_id": 8,
              "home_team_id": "9vjxm8gh613r6od",
              "away_team_id": "9k82rekhdxorepz",
              "winner_team_id": "9k82rekhdxorepz",
              "home_score": 0,
              "away_score": 5,
              "parent_ids": [
                "6ypq3nh0zd3kmd7"
              ],
              "children_ids": [],
              "event_ids": [
                "n54qllhwve6qvy9"
              ]
            },
            {
              "id": "4wyrn4h8d1o7q86",
              "round_id": "1l4rjnhkx6gm7vx",
              "number": 2,
              "type_id": 1,
              "state_id": 8,
              "home_team_id": "jw2r09hlp31rz84",
              "away_team_id": "gy0or5jhkvwqwzv",
              "winner_team_id": "gy0or5jhkvwqwzv",
              "home_score": 0,
              "away_score": 2,
              "parent_ids": [
                "6ypq3nh0zd3kmd7"
              ],
              "children_ids": [],
              "event_ids": [
                "23xmvkhl7o1qg8n"
              ]
            },
            {
              "id": "l5ergphovjl2r8k",
              "round_id": "1l4rjnhkx6gm7vx",
              "number": 3,
              "type_id": 1,
              "state_id": 8,
              "home_team_id": "z8yomo4hjwvq0j6",
              "away_team_id": "9k82rekh463repz",
              "winner_team_id": "9k82rekh463repz",
              "home_score": 0,
              "away_score": 1,
              "parent_ids": [
                "pxwrxlhg9w5nryk"
              ],
              "children_ids": [],
              "event_ids": [
                "ednm9whp1k1ryox"
              ]
            },
            {
              "id": "jw2r09hlxd69rz8",
              "round_id": "1l4rjnhkx6gm7vx",
              "number": 4,
              "type_id": 1,
              "state_id": 8,
              "home_team_id": "vjxm8gh4p87r6od",
              "away_team_id": "4zp5rzghewnq82w",
              "winner_team_id": "4zp5rzghewnq82w",
              "home_score": 0,
              "away_score": 1,
              "parent_ids": [
                "pxwrxlhg9w5nryk"
              ],
              "children_ids": [],
              "event_ids": [
                "y39mp1he753mojx"
              ]
            },
            {
              "id": "l7oqdehn4z83r51",
              "round_id": "1l4rjnhkx6gm7vx",
              "number": 5,
              "type_id": 1,
              "state_id": 8,
              "home_team_id": "v2y8m4zh9w9ql07",
              "away_team_id": "9dn1m1ghd01moep",
              "winner_team_id": "9dn1m1ghd01moep",
              "home_score": 0,
              "away_score": 3,
              "parent_ids": [
                "3glrw7hwje7gqdy"
              ],
              "children_ids": [],
              "event_ids": [
                "l5ergph7g3pr8k0"
              ]
            },
            {
              "id": "dj2ryohkj3eeq1z",
              "round_id": "1l4rjnhkx6gm7vx",
              "number": 6,
              "type_id": 1,
              "state_id": 8,
              "home_team_id": "4wyrn4h8xlpq86p",
              "away_team_id": "kdj2ryoh3wyq1zp",
              "winner_team_id": "kdj2ryoh3wyq1zp",
              "home_score": 0,
              "away_score": 2,
              "parent_ids": [
                "3glrw7hwje7gqdy"
              ],
              "children_ids": [],
              "event_ids": [
                "y0or5jhw74dqwzv"
              ]
            },
            {
              "id": "2y8m4zh3gdw6ql0",
              "round_id": "1l4rjnhkx6gm7vx",
              "number": 7,
              "type_id": 1,
              "state_id": 8,
              "home_team_id": "ednm9whkd3zryox",
              "away_team_id": "kn54qllhg3nqvy9",
              "winner_team_id": "kn54qllhg3nqvy9",
              "home_score": 0,
              "away_score": 4,
              "parent_ids": [
                "vjxm8gh4jolor6o"
              ],
              "children_ids": [],
              "event_ids": [
                "vjxm8gh7yg0r6od"
              ]
            },
            {
              "id": "8yomo4h72jg1q0j",
              "round_id": "1l4rjnhkx6gm7vx",
              "number": 8,
              "type_id": 1,
              "state_id": 8,
              "home_team_id": "jednm9wh1w6ryox",
              "away_team_id": "4zp5rzgheozq82w",
              "winner_team_id": "4zp5rzgheozq82w",
              "home_score": 1,
              "away_score": 3,
              "parent_ids": [
                "vjxm8gh4jolor6o"
              ],
              "children_ids": [],
              "event_ids": [
                "2y8m4zheljpql07"
              ]
            },
            {
              "id": "6ypq3nh0zd7kmd7",
              "round_id": "1l4rjnhkx6gm7vx",
              "number": 9,
              "type_id": 1,
              "state_id": 8,
              "home_team_id": "v2y8m4zhd2gql07",
              "away_team_id": "vl7oqdehzvnr510",
              "winner_team_id": "vl7oqdehzvnr510",
              "home_score": 1,
              "away_score": 2,
              "parent_ids": [
                "x7lm7phk0dzem2w"
              ],
              "children_ids": [],
              "event_ids": [
                "4jwq2gh5l48m0ve"
              ]
            },
            {
              "id": "pxwrxlhg9wxnryk",
              "round_id": "1l4rjnhkx6gm7vx",
              "number": 10,
              "type_id": 1,
              "state_id": 8,
              "home_team_id": "z8yomo4hop0q0j6",
              "away_team_id": "l965mkyh924r1ge",
              "winner_team_id": "l965mkyh924r1ge",
              "home_score": 0,
              "away_score": 2,
              "parent_ids": [
                "x7lm7phk0dzem2w"
              ],
              "children_ids": [],
              "event_ids": [
                "4wyrn4h5gevq86p"
              ]
            },
            {
              "id": "3glrw7hwje3gqdy",
              "round_id": "1l4rjnhkx6gm7vx",
              "number": 11,
              "type_id": 1,
              "state_id": 8,
              "home_team_id": "9dn1m1ghz7omoep",
              "away_team_id": "l965mkyh9o4r1ge",
              "winner_team_id": "l965mkyh9o4r1ge",
              "home_score": 1,
              "away_score": 2,
              "parent_ids": [
                "y0or5jhlednyqwz"
              ],
              "children_ids": [],
              "event_ids": [
                "l7oqdeh976dr510"
              ]
            },
            {
              "id": "vjxm8gh4jo5or6o",
              "round_id": "1l4rjnhkx6gm7vx",
              "number": 12,
              "type_id": 1,
              "state_id": 8,
              "home_team_id": "gpxwrxlhwy4ryk0",
              "away_team_id": "z318q66hdp1qo9j",
              "winner_team_id": "z318q66hdp1qo9j",
              "home_score": 1,
              "away_score": 2,
              "parent_ids": [
                "y0or5jhlednyqwz"
              ],
              "children_ids": [],
              "event_ids": [
                "zp5rzghd87kq82w"
              ]
            },
            {
              "id": "x7lm7phk0d3em2w",
              "round_id": "1l4rjnhkx6gm7vx",
              "number": 13,
              "type_id": 1,
              "state_id": 7,
              "home_team_id": "gy0or5jhkolqwzv",
              "away_team_id": "kn54qllhylpqvy9",
              "winner_team_id": "gy0or5jhkolqwzv",
              "home_score": 3,
              "away_score": 1,
              "parent_ids": [
                "n54qllh2xy70qvy"
              ],
              "children_ids": [],
              "event_ids": [
                "ednm9whp191ryox"
              ]
            },
            {
              "id": "y0or5jhledzyqwz",
              "round_id": "1l4rjnhkx6gm7vx",
              "number": 14,
              "type_id": 1,
              "state_id": 8,
              "home_team_id": "kdj2ryoh0l3q1zp",
              "away_team_id": "kjw2r09hd99rz84",
              "winner_team_id": "kjw2r09hd99rz84",
              "home_score": 0,
              "away_score": 3,
              "parent_ids": [
                "n54qllh2xy70qvy"
              ],
              "children_ids": [],
              "event_ids": [
                "dj2ryoh98y4q1zp"
              ]
            },
            {
              "id": "n54qllh2xyp0qvy",
              "round_id": "1l4rjnhkx6gm7vx",
              "number": 15,
              "type_id": 1,
              "state_id": 8,
              "home_team_id": "jw2r09hllz9rz84",
              "away_team_id": "yl5ergphj74r8k0",
              "winner_team_id": "yl5ergphj74r8k0",
              "home_score": 0,
              "away_score": 3,
              "parent_ids": [
                "23xmvkh3dz8nqg8"
              ],
              "children_ids": [],
              "event_ids": [
                "318q66h3lvvqo9j"
              ]
            },
            {
              "id": "23xmvkh3dzpnqg8",
              "round_id": "1l4rjnhkx6gm7vx",
              "number": 16,
              "type_id": 1,
              "state_id": 8,
              "home_team_id": "gpxwrxlho42ryk0",
              "away_team_id": "56ypq3nhdnkmd7o",
              "winner_team_id": "56ypq3nhdnkmd7o",
              "home_score": 1,
              "away_score": 4,
              "parent_ids": [
                "23xmvkh3dz8nqg8"
              ],
              "children_ids": [],
              "event_ids": [
                "965mkyh0p4lr1ge"
              ]
            },
            {
              "id": "zp5rzghjze6nq82",
              "round_id": "1l4rjnhkx6gm7vx",
              "number": 17,
              "type_id": 1,
              "state_id": 7,
              "home_team_id": "gpxwrxlho9xryk0",
              "away_team_id": "d23xmvkhze8qg8n",
              "winner_team_id": "gpxwrxlho9xryk0",
              "home_score": 2,
              "away_score": 1,
              "parent_ids": [
                "zp5rzghjze5nq82"
              ],
              "children_ids": [],
              "event_ids": [
                "1l4rjnhdv6wm7vx"
              ]
            },
            {
              "id": "1l4rjnh6zpjvm7v",
              "round_id": "1l4rjnhkx6gm7vx",
              "number": 18,
              "type_id": 1,
              "state_id": 8,
              "home_team_id": "v2y8m4zh9vlql07",
              "away_team_id": "gy0or5jhdoyqwzv",
              "winner_team_id": "gy0or5jhdoyqwzv",
              "home_score": 4,
              "away_score": 7,
              "parent_ids": [
                "zp5rzghjze5nq82"
              ],
              "children_ids": [],
              "event_ids": [
                "k82rekhjly9repz"
              ]
            },
            {
              "id": "4jwq2gh4vdeom0v",
              "round_id": "1l4rjnhkx6gm7vx",
              "number": 19,
              "type_id": 1,
              "state_id": 8,
              "home_team_id": "y39mp1h3132mojx",
              "away_team_id": "z318q66hp2kqo9j",
              "winner_team_id": "z318q66hp2kqo9j",
              "home_score": 0,
              "away_score": 2,
              "parent_ids": [
                "1l4rjnh6zp4vm7v"
              ],
              "children_ids": [],
              "event_ids": [
                "8yomo4h6nkgq0j6"
              ]
            },
            {
              "id": "ednm9whkzl7kryo",
              "round_id": "1l4rjnhkx6gm7vx",
              "number": 20,
              "type_id": 1,
              "state_id": 8,
              "home_team_id": "2y8m4zhj08lql07",
              "away_team_id": "4zp5rzghe4nq82w",
              "winner_team_id": "4zp5rzghe4nq82w",
              "home_score": 1,
              "away_score": 3,
              "parent_ids": [
                "1l4rjnh6zp4vm7v"
              ],
              "children_ids": [],
              "event_ids": [
                "dn1m1ghg6e3moep"
              ]
            },
            {
              "id": "965mkyh739y4r1g",
              "round_id": "1l4rjnhkx6gm7vx",
              "number": 21,
              "type_id": 1,
              "state_id": 8,
              "home_team_id": "kn54qllh6lyqvy9",
              "away_team_id": "z318q66hp7kqo9j",
              "winner_team_id": "z318q66hp7kqo9j",
              "home_score": 0,
              "away_score": 1,
              "parent_ids": [
                "4jwq2gh4vdnom0v"
              ],
              "children_ids": [],
              "event_ids": [
                "jw2r09hg8nprz84"
              ]
            },
            {
              "id": "y39mp1h3j8zjmoj",
              "round_id": "1l4rjnhkx6gm7vx",
              "number": 22,
              "type_id": 1,
              "state_id": 8,
              "home_team_id": "p3glrw7h580qdyj",
              "away_team_id": "gpxwrxlhw3nryk0",
              "winner_team_id": "gpxwrxlhw3nryk0",
              "home_score": 1,
              "away_score": 3,
              "parent_ids": [
                "4jwq2gh4vdnom0v"
              ],
              "children_ids": [],
              "event_ids": [
                "pxwrxlh0d1yryk0"
              ]
            },
            {
              "id": "k82rekhvydworep",
              "round_id": "1l4rjnhkx6gm7vx",
              "number": 23,
              "type_id": 1,
              "state_id": 8,
              "home_team_id": "318q66howgdqo9j",
              "away_team_id": "kn54qllhy10qvy9",
              "winner_team_id": "kn54qllhy10qvy9",
              "home_score": 0,
              "away_score": 1,
              "parent_ids": [
                "ednm9whkzlwkryo"
              ],
              "children_ids": [],
              "event_ids": [
                "965mkyh0p3lr1ge"
              ]
            },
            {
              "id": "318q66hovdwjqo9",
              "round_id": "1l4rjnhkx6gm7vx",
              "number": 24,
              "type_id": 1,
              "state_id": 8,
              "home_team_id": "n54qllh2d1dqvy9",
              "away_team_id": "gpxwrxlhwkvryk0",
              "winner_team_id": "gpxwrxlhwkvryk0",
              "home_score": 0,
              "away_score": 4,
              "parent_ids": [
                "ednm9whkzlwkryo"
              ],
              "children_ids": [],
              "event_ids": [
                "3glrw7hgd14qdyj"
              ]
            },
            {
              "id": "dn1m1gh4nd21moe",
              "round_id": "1l4rjnhkx6gm7vx",
              "number": 25,
              "type_id": 1,
              "state_id": 8,
              "home_team_id": "gpxwrxlhojxryk0",
              "away_team_id": "p3glrw7henvqdyj",
              "winner_team_id": "p3glrw7henvqdyj",
              "home_score": 0,
              "away_score": 3,
              "parent_ids": [
                "965mkyh739k4r1g"
              ],
              "children_ids": [],
              "event_ids": [
                "4jwq2gh5lk8m0ve"
              ]
            },
            {
              "id": "4wyrn4h8d1x7q86",
              "round_id": "1l4rjnhkx6gm7vx",
              "number": 26,
              "type_id": 1,
              "state_id": 8,
              "home_team_id": "3glrw7hwlnnqdyj",
              "away_team_id": "v2y8m4zh959ql07",
              "winner_team_id": "v2y8m4zh959ql07",
              "home_score": 1,
              "away_score": 4,
              "parent_ids": [
                "965mkyh739k4r1g"
              ],
              "children_ids": [],
              "event_ids": [
                "dn1m1ghg6n3moep"
              ]
            },
            {
              "id": "l5ergphovjw2r8k",
              "round_id": "1l4rjnhkx6gm7vx",
              "number": 27,
              "type_id": 1,
              "state_id": 8,
              "home_team_id": "n54qllh20zlqvy9",
              "away_team_id": "yl5ergphjy2r8k0",
              "winner_team_id": "yl5ergphjy2r8k0",
              "home_score": 1,
              "away_score": 3,
              "parent_ids": [
                "y39mp1h3j86jmoj"
              ],
              "children_ids": [],
              "event_ids": [
                "y39mp1he7j3mojx"
              ]
            },
            {
              "id": "jw2r09hlxd29rz8",
              "round_id": "1l4rjnhkx6gm7vx",
              "number": 28,
              "type_id": 1,
              "state_id": 8,
              "home_team_id": "l5ergphon6zr8k0",
              "away_team_id": "p4jwq2ghdw7m0ve",
              "winner_team_id": "p4jwq2ghdw7m0ve",
              "home_score": 0,
              "away_score": 3,
              "parent_ids": [
                "y39mp1h3j86jmoj"
              ],
              "children_ids": [],
              "event_ids": [
                "x7lm7ph24o2m2wd"
              ]
            },
            {
              "id": "l7oqdehn4zo3r51",
              "round_id": "1l4rjnhkx6gm7vx",
              "number": 29,
              "type_id": 1,
              "state_id": 8,
              "home_team_id": "jednm9whloeryox",
              "away_team_id": "z8yomo4hoglq0j6",
              "winner_team_id": "z8yomo4hoglq0j6",
              "home_score": 5,
              "away_score": 6,
              "parent_ids": [
                "k82rekhvydgorep"
              ],
              "children_ids": [],
              "event_ids": [
                "6ypq3nhpx53md7o"
              ]
            },
            {
              "id": "dj2ryohkj31eq1z",
              "round_id": "1l4rjnhkx6gm7vx",
              "number": 30,
              "type_id": 1,
              "state_id": 8,
              "home_team_id": "pxwrxlhg21kryk0",
              "away_team_id": "kdj2ryoh379q1zp",
              "winner_team_id": "kdj2ryoh379q1zp",
              "home_score": 0,
              "away_score": 1,
              "parent_ids": [
                "k82rekhvydgorep"
              ],
              "children_ids": [],
              "event_ids": [
                "1l4rjnhdv1wm7vx"
              ]
            },
            {
              "id": "2y8m4zh3gd66ql0",
              "round_id": "1l4rjnhkx6gm7vx",
              "number": 31,
              "type_id": 1,
              "state_id": 7,
              "home_team_id": "z8yomo4ho2xq0j6",
              "away_team_id": "jednm9whl2kryox",
              "winner_team_id": "z8yomo4ho2xq0j6",
              "home_score": 2,
              "away_score": 1,
              "parent_ids": [
                "318q66hovdxjqo9"
              ],
              "children_ids": [],
              "event_ids": [
                "k82rekhjl99repz"
              ]
            },
            {
              "id": "8yomo4h72j31q0j",
              "round_id": "1l4rjnhkx6gm7vx",
              "number": 32,
              "type_id": 1,
              "state_id": 8,
              "home_team_id": "1l4rjnh6p44m7vx",
              "away_team_id": "gx7lm7phd7em2wd",
              "winner_team_id": "gx7lm7phd7em2wd",
              "home_score": 1,
              "away_score": 4,
              "parent_ids": [
                "318q66hovdxjqo9"
              ],
              "children_ids": [],
              "event_ids": [
                "318q66h3l0vqo9j"
              ]
            }
          ]
        },
        {
          "id": "4jwq2gh7x45m0ve",
          "bracket_id": "965mkyh7xvgr1ge",
          "name": "Round2",
          "abbr": "R2",
          "start_time": 1253638800,
          "end_time": 1253730600,
          "number": 2,
          "match_ups": [
            {
              "id": "6ypq3nh0zd3kmd7",
              "round_id": "4jwq2gh7x45m0ve",
              "number": 1,
              "type_id": 1,
              "state_id": 7,
              "home_team_id": "9k82rekhdxorepz",
              "away_team_id": "gy0or5jhkvwqwzv",
              "winner_team_id": "9k82rekhdxorepz",
              "home_score": 2,
              "away_score": 1,
              "parent_ids": [
                "dn1m1gh4ndl1moe"
              ],
              "children_ids": [
                "dn1m1gh4ndp1moe",
                "4wyrn4h8d1o7q86"
              ],
              "event_ids": [
                "vjxm8gh7y40r6od"
              ]
            },
            {
              "id": "pxwrxlhg9w5nryk",
              "round_id": "4jwq2gh7x45m0ve",
              "number": 2,
              "type_id": 1,
              "state_id": 7,
              "home_team_id": "9k82rekh463repz",
              "away_team_id": "4zp5rzghewnq82w",
              "winner_team_id": "9k82rekh463repz",
              "home_score": 2,
              "away_score": 1,
              "parent_ids": [
                "dn1m1gh4ndl1moe"
              ],
              "children_ids": [
                "l5ergphovjl2r8k",
                "jw2r09hlxd69rz8"
              ],
              "event_ids": [
                "23xmvkhl731qg8n"
              ]
            },
            {
              "id": "3glrw7hwje7gqdy",
              "round_id": "4jwq2gh7x45m0ve",
              "number": 3,
              "type_id": 1,
              "state_id": 8,
              "home_team_id": "9dn1m1ghd01moep",
              "away_team_id": "kdj2ryoh3wyq1zp",
              "winner_team_id": "kdj2ryoh3wyq1zp",
              "home_score": 0,
              "away_score": 1,
              "parent_ids": [
                "4wyrn4h8d167q86"
              ],
              "children_ids": [
                "l7oqdehn4z83r51",
                "dj2ryohkj3eeq1z"
              ],
              "event_ids": [
                "l5ergph7gopr8k0"
              ]
            },
            {
              "id": "vjxm8gh4jolor6o",
              "round_id": "4jwq2gh7x45m0ve",
              "number": 4,
              "type_id": 1,
              "state_id": 7,
              "home_team_id": "kn54qllhg3nqvy9",
              "away_team_id": "4zp5rzgheozq82w",
              "winner_team_id": "kn54qllhg3nqvy9",
              "home_score": 4,
              "away_score": 2,
              "parent_ids": [
                "4wyrn4h8d167q86"
              ],
              "children_ids": [
                "2y8m4zh3gdw6ql0",
                "8yomo4h72jg1q0j"
              ],
              "event_ids": [
                "6ypq3nhpx03md7o"
              ]
            },
            {
              "id": "x7lm7phk0dzem2w",
              "round_id": "4jwq2gh7x45m0ve",
              "number": 5,
              "type_id": 1,
              "state_id": 7,
              "home_team_id": "vl7oqdehzvnr510",
              "away_team_id": "l965mkyh924r1ge",
              "winner_team_id": "vl7oqdehzvnr510",
              "home_score": 1,
              "away_score": 0,
              "parent_ids": [
                "l5ergphovj42r8k"
              ],
              "children_ids": [
                "6ypq3nh0zd7kmd7",
                "pxwrxlhg9wxnryk"
              ],
              "event_ids": [
                "3glrw7hgdw4qdyj"
              ]
            },
            {
              "id": "y0or5jhlednyqwz",
              "round_id": "4jwq2gh7x45m0ve",
              "number": 6,
              "type_id": 1,
              "state_id": 8,
              "home_team_id": "l965mkyh9o4r1ge",
              "away_team_id": "z318q66hdp1qo9j",
              "winner_team_id": "z318q66hdp1qo9j",
              "home_score": 0,
              "away_score": 1,
              "parent_ids": [
                "l5ergphovj42r8k"
              ],
              "children_ids": [
                "3glrw7hwje3gqdy",
                "vjxm8gh4jo5or6o"
              ],
              "event_ids": [
                "l7oqdeh97ndr510"
              ]
            },
            {
              "id": "n54qllh2xy70qvy",
              "round_id": "4jwq2gh7x45m0ve",
              "number": 7,
              "type_id": 1,
              "state_id": 7,
              "home_team_id": "gy0or5jhkolqwzv",
              "away_team_id": "kjw2r09hd99rz84",
              "winner_team_id": "gy0or5jhkolqwzv",
              "home_score": 4,
              "away_score": 2,
              "parent_ids": [
                "jw2r09hlxdk9rz8"
              ],
              "children_ids": [
                "x7lm7phk0d3em2w",
                "y0or5jhledzyqwz"
              ],
              "event_ids": [
                "4wyrn4h5g8vq86p"
              ]
            },
            {
              "id": "23xmvkh3dz8nqg8",
              "round_id": "4jwq2gh7x45m0ve",
              "number": 8,
              "type_id": 1,
              "state_id": 7,
              "home_team_id": "yl5ergphj74r8k0",
              "away_team_id": "56ypq3nhdnkmd7o",
              "winner_team_id": "yl5ergphj74r8k0",
              "home_score": 3,
              "away_score": 2,
              "parent_ids": [
                "jw2r09hlxdk9rz8"
              ],
              "children_ids": [
                "n54qllh2xyp0qvy",
                "23xmvkh3dzpnqg8"
              ],
              "event_ids": [
                "zp5rzghd8jkq82w"
              ]
            },
            {
              "id": "zp5rzghjze5nq82",
              "round_id": "4jwq2gh7x45m0ve",
              "number": 9,
              "type_id": 1,
              "state_id": 7,
              "home_team_id": "gpxwrxlho9xryk0",
              "away_team_id": "gy0or5jhdoyqwzv",
              "winner_team_id": "gpxwrxlho9xryk0",
              "home_score": 7,
              "away_score": 5,
              "parent_ids": [
                "l7oqdehn4zg3r51"
              ],
              "children_ids": [
                "zp5rzghjze6nq82",
                "1l4rjnh6zpjvm7v"
              ],
              "event_ids": [
                "y0or5jhw7ldqwzv"
              ]
            },
            {
              "id": "1l4rjnh6zp4vm7v",
              "round_id": "4jwq2gh7x45m0ve",
              "number": 10,
              "type_id": 1,
              "state_id": 8,
              "home_team_id": "z318q66hp2kqo9j",
              "away_team_id": "4zp5rzghe4nq82w",
              "winner_team_id": "4zp5rzghe4nq82w",
              "home_score": 0,
              "away_score": 3,
              "parent_ids": [
                "l7oqdehn4zg3r51"
              ],
              "children_ids": [
                "4jwq2gh4vdeom0v",
                "ednm9whkzl7kryo"
              ],
              "event_ids": [
                "2y8m4zhel3pql07"
              ]
            },
            {
              "id": "4jwq2gh4vdnom0v",
              "round_id": "4jwq2gh7x45m0ve",
              "number": 11,
              "type_id": 1,
              "state_id": 7,
              "home_team_id": "z318q66hp7kqo9j",
              "away_team_id": "gpxwrxlhw3nryk0",
              "winner_team_id": "z318q66hp7kqo9j",
              "home_score": 6,
              "away_score": 3,
              "parent_ids": [
                "dj2ryohkj3leq1z"
              ],
              "children_ids": [
                "965mkyh739y4r1g",
                "y39mp1h3j8zjmoj"
              ],
              "event_ids": [
                "pxwrxlh0dgyryk0"
              ]
            },
            {
              "id": "ednm9whkzlwkryo",
              "round_id": "4jwq2gh7x45m0ve",
              "number": 12,
              "type_id": 1,
              "state_id": 8,
              "home_team_id": "kn54qllhy10qvy9",
              "away_team_id": "gpxwrxlhwkvryk0",
              "winner_team_id": "gpxwrxlhwkvryk0",
              "home_score": 0,
              "away_score": 3,
              "parent_ids": [
                "dj2ryohkj3leq1z"
              ],
              "children_ids": [
                "k82rekhvydworep",
                "318q66hovdwjqo9"
              ],
              "event_ids": [
                "8yomo4h6n7gq0j6"
              ]
            },
            {
              "id": "965mkyh739k4r1g",
              "round_id": "4jwq2gh7x45m0ve",
              "number": 13,
              "type_id": 1,
              "state_id": 7,
              "home_team_id": "p3glrw7henvqdyj",
              "away_team_id": "v2y8m4zh959ql07",
              "winner_team_id": "p3glrw7henvqdyj",
              "home_score": 6,
              "away_score": 4,
              "parent_ids": [
                "2y8m4zh3gd56ql0"
              ],
              "children_ids": [
                "dn1m1gh4nd21moe",
                "4wyrn4h8d1x7q86"
              ],
              "event_ids": [
                "x7lm7ph24k2m2wd"
              ]
            },
            {
              "id": "y39mp1h3j86jmoj",
              "round_id": "4jwq2gh7x45m0ve",
              "number": 14,
              "type_id": 1,
              "state_id": 7,
              "home_team_id": "yl5ergphjy2r8k0",
              "away_team_id": "p4jwq2ghdw7m0ve",
              "winner_team_id": "yl5ergphjy2r8k0",
              "home_score": 5,
              "away_score": 0,
              "parent_ids": [
                "2y8m4zh3gd56ql0"
              ],
              "children_ids": [
                "l5ergphovjw2r8k",
                "jw2r09hlxd29rz8"
              ],
              "event_ids": [
                "jw2r09hg8lprz84"
              ]
            },
            {
              "id": "k82rekhvydgorep",
              "round_id": "4jwq2gh7x45m0ve",
              "number": 15,
              "type_id": 1,
              "state_id": 8,
              "home_team_id": "z8yomo4hoglq0j6",
              "away_team_id": "kdj2ryoh379q1zp",
              "winner_team_id": "kdj2ryoh379q1zp",
              "home_score": 2,
              "away_score": 3,
              "parent_ids": [
                "8yomo4h72j11q0j"
              ],
              "children_ids": [
                "l7oqdehn4zo3r51",
                "dj2ryohkj31eq1z"
              ],
              "event_ids": [
                "dj2ryoh98k4q1zp"
              ]
            },
            {
              "id": "318q66hovdxjqo9",
              "round_id": "4jwq2gh7x45m0ve",
              "number": 16,
              "type_id": 1,
              "state_id": 8,
              "home_team_id": "z8yomo4ho2xq0j6",
              "away_team_id": "gx7lm7phd7em2wd",
              "winner_team_id": "gx7lm7phd7em2wd",
              "home_score": 1,
              "away_score": 3,
              "parent_ids": [
                "8yomo4h72j11q0j"
              ],
              "children_ids": [
                "2y8m4zh3gd66ql0",
                "8yomo4h72j31q0j"
              ],
              "event_ids": [
                "n54qllhwv26qvy9"
              ]
            }
          ]
        },
        {
          "id": "ednm9whgvklryox",
          "bracket_id": "965mkyh7xvgr1ge",
          "name": "1/8 Finals",
          "abbr": "R16",
          "start_time": 1256666400,
          "end_time": 1256758200,
          "number": 3,
          "match_ups": [
            {
              "id": "dn1m1gh4ndl1moe",
              "round_id": "ednm9whgvklryox",
              "number": 1,
              "type_id": 1,
              "state_id": 7,
              "home_team_id": "9k82rekhdxorepz",
              "away_team_id": "9k82rekh463repz",
              "winner_team_id": "9k82rekhdxorepz",
              "home_score": 3,
              "away_score": 0,
              "parent_ids": [
                "6ypq3nh0zdvkmd7"
              ],
              "children_ids": [
                "6ypq3nh0zd3kmd7",
                "pxwrxlhg9w5nryk"
              ],
              "event_ids": [
                "dj2ryohdj0vjq1z"
              ]
            },
            {
              "id": "4wyrn4h8d167q86",
              "round_id": "ednm9whgvklryox",
              "number": 2,
              "type_id": 1,
              "state_id": 7,
              "home_team_id": "kdj2ryoh3wyq1zp",
              "away_team_id": "kn54qllhg3nqvy9",
              "winner_team_id": "kdj2ryoh3wyq1zp",
              "home_score": 4,
              "away_score": 0,
              "parent_ids": [
                "6ypq3nh0zdvkmd7"
              ],
              "children_ids": [
                "3glrw7hwje7gqdy",
                "vjxm8gh4jolor6o"
              ],
              "event_ids": [
                "2y8m4zh4g908ql0"
              ]
            },
            {
              "id": "l5ergphovj42r8k",
              "round_id": "ednm9whgvklryox",
              "number": 3,
              "type_id": 1,
              "state_id": 7,
              "home_team_id": "vl7oqdehzvnr510",
              "away_team_id": "z318q66hdp1qo9j",
              "winner_team_id": "vl7oqdehzvnr510",
              "home_score": 5,
              "away_score": 0,
              "parent_ids": [
                "pxwrxlhg9wynryk"
              ],
              "children_ids": [
                "x7lm7phk0dzem2w",
                "y0or5jhlednyqwz"
              ],
              "event_ids": [
                "6ypq3nh4zdx1md7"
              ]
            },
            {
              "id": "jw2r09hlxdk9rz8",
              "round_id": "ednm9whgvklryox",
              "number": 4,
              "type_id": 1,
              "state_id": 8,
              "home_team_id": "gy0or5jhkolqwzv",
              "away_team_id": "yl5ergphj74r8k0",
              "winner_team_id": "yl5ergphj74r8k0",
              "home_score": 0,
              "away_score": 3,
              "parent_ids": [
                "pxwrxlhg9wynryk"
              ],
              "children_ids": [
                "n54qllh2xy70qvy",
                "23xmvkh3dz8nqg8"
              ],
              "event_ids": [
                "l7oqdehe4z76r51"
              ]
            },
            {
              "id": "l7oqdehn4zg3r51",
              "round_id": "ednm9whgvklryox",
              "number": 5,
              "type_id": 1,
              "state_id": 7,
              "home_team_id": "gpxwrxlho9xryk0",
              "away_team_id": "4zp5rzghe4nq82w",
              "winner_team_id": "gpxwrxlho9xryk0",
              "home_score": 3,
              "away_score": 2,
              "parent_ids": [
                "3glrw7hwjengqdy"
              ],
              "children_ids": [
                "zp5rzghjze5nq82",
                "1l4rjnh6zp4vm7v"
              ],
              "event_ids": [
                "8yomo4h52jn0q0j"
              ]
            },
            {
              "id": "dj2ryohkj3leq1z",
              "round_id": "ednm9whgvklryox",
              "number": 6,
              "type_id": 1,
              "state_id": 8,
              "home_team_id": "z318q66hp7kqo9j",
              "away_team_id": "gpxwrxlhwkvryk0",
              "winner_team_id": "gpxwrxlhwkvryk0",
              "home_score": 0,
              "away_score": 3,
              "parent_ids": [
                "3glrw7hwjengqdy"
              ],
              "children_ids": [
                "4jwq2gh4vdnom0v",
                "ednm9whkzlwkryo"
              ],
              "event_ids": [
                "l7oqdehe4ky6r51"
              ]
            },
            {
              "id": "2y8m4zh3gd56ql0",
              "round_id": "ednm9whgvklryox",
              "number": 7,
              "type_id": 1,
              "state_id": 8,
              "home_team_id": "p3glrw7henvqdyj",
              "away_team_id": "yl5ergphjy2r8k0",
              "winner_team_id": "yl5ergphjy2r8k0",
              "home_score": 0,
              "away_score": 4,
              "parent_ids": [
                "vjxm8gh4joeor6o"
              ],
              "children_ids": [
                "965mkyh739k4r1g",
                "y39mp1h3j86jmoj"
              ],
              "event_ids": [
                "8yomo4h52oe0q0j"
              ]
            },
            {
              "id": "8yomo4h72j11q0j",
              "round_id": "ednm9whgvklryox",
              "number": 8,
              "type_id": 1,
              "state_id": 7,
              "home_team_id": "kdj2ryoh379q1zp",
              "away_team_id": "gx7lm7phd7em2wd",
              "winner_team_id": "kdj2ryoh379q1zp",
              "home_score": 1,
              "away_score": 0,
              "parent_ids": [
                "vjxm8gh4joeor6o"
              ],
              "children_ids": [
                "k82rekhvydgorep",
                "318q66hovdxjqo9"
              ],
              "event_ids": [
                "dj2ryohdj38jq1z"
              ]
            }
          ]
        },
        {
          "id": "965mkyhne7xr1ge",
          "bracket_id": "965mkyh7xvgr1ge",
          "name": "Quarterfinals",
          "abbr": "QF",
          "start_time": 1265743800,
          "end_time": 1265830200,
          "number": 4,
          "match_ups": [
            {
              "id": "6ypq3nh0zdvkmd7",
              "round_id": "965mkyhne7xr1ge",
              "number": 1,
              "type_id": 1,
              "state_id": 7,
              "home_team_id": "9k82rekhdxorepz",
              "away_team_id": "kdj2ryoh3wyq1zp",
              "winner_team_id": "9k82rekhdxorepz",
              "home_score": 2,
              "away_score": 1,
              "parent_ids": [
                "x7lm7phk0djem2w"
              ],
              "children_ids": [
                "dn1m1gh4ndl1moe",
                "4wyrn4h8d167q86"
              ],
              "event_ids": [
                "jw2r09hg8xprz84"
              ]
            },
            {
              "id": "pxwrxlhg9wynryk",
              "round_id": "965mkyhne7xr1ge",
              "number": 2,
              "type_id": 1,
              "state_id": 7,
              "home_team_id": "vl7oqdehzvnr510",
              "away_team_id": "yl5ergphj74r8k0",
              "winner_team_id": "vl7oqdehzvnr510",
              "home_score": 2,
              "away_score": 0,
              "parent_ids": [
                "x7lm7phk0djem2w"
              ],
              "children_ids": [
                "l5ergphovj42r8k",
                "jw2r09hlxdk9rz8"
              ],
              "event_ids": [
                "dj2ryoh98j4q1zp"
              ]
            },
            {
              "id": "3glrw7hwjengqdy",
              "round_id": "965mkyhne7xr1ge",
              "number": 3,
              "type_id": 1,
              "state_id": 8,
              "home_team_id": "gpxwrxlho9xryk0",
              "away_team_id": "gpxwrxlhwkvryk0",
              "winner_team_id": "gpxwrxlhwkvryk0",
              "home_score": 0,
              "away_score": 1,
              "parent_ids": [
                "y0or5jhled8yqwz"
              ],
              "children_ids": [
                "l7oqdehn4zg3r51",
                "dj2ryohkj3leq1z"
              ],
              "event_ids": [
                "2y8m4zhelgpql07"
              ]
            },
            {
              "id": "vjxm8gh4joeor6o",
              "round_id": "965mkyhne7xr1ge",
              "number": 4,
              "type_id": 1,
              "state_id": 7,
              "home_team_id": "yl5ergphjy2r8k0",
              "away_team_id": "kdj2ryoh379q1zp",
              "winner_team_id": "yl5ergphjy2r8k0",
              "home_score": 6,
              "away_score": 2,
              "parent_ids": [
                "y0or5jhled8yqwz"
              ],
              "children_ids": [
                "2y8m4zh3gd56ql0",
                "8yomo4h72j11q0j"
              ],
              "event_ids": [
                "l7oqdeh974dr510"
              ]
            }
          ]
        },
        {
          "id": "y39mp1h1y3gmojx",
          "bracket_id": "965mkyh7xvgr1ge",
          "name": "Semi Finals",
          "abbr": "SF",
          "start_time": 1269372600,
          "end_time": 1269459000,
          "number": 5,
          "match_ups": [
            {
              "id": "x7lm7phk0djem2w",
              "round_id": "y39mp1h1y3gmojx",
              "number": 1,
              "type_id": 1,
              "state_id": 7,
              "home_team_id": "9k82rekhdxorepz",
              "away_team_id": "vl7oqdehzvnr510",
              "winner_team_id": "9k82rekhdxorepz",
              "home_score": 2,
              "away_score": 0,
              "parent_ids": [
                "n54qllh2xyn0qvy"
              ],
              "children_ids": [
                "6ypq3nh0zdvkmd7",
                "pxwrxlhg9wynryk"
              ],
              "event_ids": [
                "4wyrn4h5gdvq86p"
              ]
            },
            {
              "id": "y0or5jhled8yqwz",
              "round_id": "y39mp1h1y3gmojx",
              "number": 2,
              "type_id": 1,
              "state_id": 8,
              "home_team_id": "gpxwrxlhwkvryk0",
              "away_team_id": "yl5ergphjy2r8k0",
              "winner_team_id": "yl5ergphjy2r8k0",
              "home_score": 0,
              "away_score": 1,
              "parent_ids": [
                "n54qllh2xyn0qvy"
              ],
              "children_ids": [
                "3glrw7hwjengqdy",
                "vjxm8gh4joeor6o"
              ],
              "event_ids": [
                "l5ergph7gvpr8k0"
              ]
            }
          ]
        },
        {
          "id": "k82rekh3ovkrepz",
          "bracket_id": "965mkyh7xvgr1ge",
          "name": "Final",
          "abbr": "F",
          "start_time": 1273946400,
          "end_time": 1273946400,
          "number": 6,
          "match_ups": [
            {
              "id": "n54qllh2xyn0qvy",
              "round_id": "k82rekh3ovkrepz",
              "number": 1,
              "type_id": 1,
              "state_id": 8,
              "home_team_id": "9k82rekhdxorepz",
              "away_team_id": "yl5ergphjy2r8k0",
              "winner_team_id": "yl5ergphjy2r8k0",
              "home_score": 0,
              "away_score": 4,
              "parent_ids": [],
              "children_ids": [
                "x7lm7phk0djem2w",
                "y0or5jhled8yqwz"
              ],
              "event_ids": [
                "8yomo4h6n2gq0j6"
              ]
            }
          ]
        }
      ]
    }
  ],
  "competitors": {
    "jw2r09hlp31rz84": {
      "id": "jw2r09hlp31rz84",
      "name": "Villingen"
    },
    "56ypq3nhdnkmd7o": {
      "id": "56ypq3nhdnkmd7o",
      "name": "VfL Wolfsburg"
    },
    "gx7lm7phd7em2wd": {
      "id": "gx7lm7phd7em2wd",
      "name": "VfB Stuttgart"
    },
    "gpxwrxlhwy4ryk0": {
      "id": "gpxwrxlhwy4ryk0",
      "name": "Rot-Weiss Erfurt"
    },
    "gpxwrxlho9xryk0": {
      "id": "gpxwrxlho9xryk0",
      "name": "VfL Osnabrück"
    },
    "gpxwrxlho42ryk0": {
      "id": "gpxwrxlho42ryk0",
      "name": "SV Wehen Wiesbaden"
    },
    "kdj2ryoh0l3q1zp": {
      "id": "kdj2ryoh0l3q1zp",
      "name": "Unterhaching"
    },
    "p3glrw7h580qdyj": {
      "id": "p3glrw7h580qdyj",
      "name": "Preuben Munster"
    },
    "kn54qllhylpqvy9": {
      "id": "kn54qllhylpqvy9",
      "name": "Hannover 96"
    },
    "jednm9whloeryox": {
      "id": "jednm9whloeryox",
      "name": "Wacker Burghausen"
    },
    "gpxwrxlhojxryk0": {
      "id": "gpxwrxlhojxryk0",
      "name": "Kickers Offenbach"
    },
    "yl5ergphjy2r8k0": {
      "id": "yl5ergphjy2r8k0",
      "name": "FC Bayern Munich"
    },
    "pxwrxlhg21kryk0": {
      "id": "pxwrxlhg21kryk0",
      "name": "VfR Wormatia Worms"
    },
    "gy0or5jhkolqwzv": {
      "id": "gy0or5jhkolqwzv",
      "name": "Eintracht Trier"
    },
    "vl7oqdehzvnr510": {
      "id": "vl7oqdehzvnr510",
      "name": "FC Augsburg"
    },
    "yl5ergphj74r8k0": {
      "id": "yl5ergphj74r8k0",
      "name": "FC Köln"
    },
    "kn54qllhg3nqvy9": {
      "id": "kn54qllhg3nqvy9",
      "name": "TuS Koblenz"
    },
    "9vjxm8gh613r6od": {
      "id": "9vjxm8gh613r6od",
      "name": "1. FC Union Berlin"
    },
    "l965mkyh924r1ge": {
      "id": "l965mkyh924r1ge",
      "name": "SC Freiburg"
    },
    "l5ergphon6zr8k0": {
      "id": "l5ergphon6zr8k0",
      "name": "VfB Speldorf"
    },
    "2y8m4zhj08lql07": {
      "id": "2y8m4zhj08lql07",
      "name": "SpVgg Weiden"
    },
    "n54qllh2d1dqvy9": {
      "id": "n54qllh2d1dqvy9",
      "name": "TSV Germania Windeck"
    },
    "kn54qllhy10qvy9": {
      "id": "kn54qllhy10qvy9",
      "name": "VfL Bochum 1848"
    },
    "3glrw7hwlnnqdyj": {
      "id": "3glrw7hwlnnqdyj",
      "name": "Torgelower FC Greif"
    },
    "ednm9whkd3zryox": {
      "id": "ednm9whkd3zryox",
      "name": "SC Concordia Hamburg"
    },
    "4zp5rzgheozq82w": {
      "id": "4zp5rzgheozq82w",
      "name": "Energie Cottbus"
    },
    "9dn1m1ghz7omoep": {
      "id": "9dn1m1ghz7omoep",
      "name": "FSV Frankfurt"
    },
    "n54qllh20zlqvy9": {
      "id": "n54qllh20zlqvy9",
      "name": "SpVgg Neckarelz"
    },
    "9k82rekh463repz": {
      "id": "9k82rekh463repz",
      "name": "1. FC Kaiserslautern"
    },
    "v2y8m4zh959ql07": {
      "id": "v2y8m4zh959ql07",
      "name": "Alemannia Aachen"
    },
    "318q66howgdqo9j": {
      "id": "318q66howgdqo9j",
      "name": "Sportfreunde Lotte"
    },
    "9k82rekhdxorepz": {
      "id": "9k82rekhdxorepz",
      "name": "SV Werder Bremen"
    },
    "y39mp1h3132mojx": {
      "id": "y39mp1h3132mojx",
      "name": "Tennis Borussia Berlin"
    },
    "z318q66hp7kqo9j": {
      "id": "z318q66hp7kqo9j",
      "name": "TSV 1860 München"
    },
    "gy0or5jhdoyqwzv": {
      "id": "gy0or5jhdoyqwzv",
      "name": "Hamburger SV"
    },
    "1l4rjnh6p44m7vx": {
      "id": "1l4rjnh6p44m7vx",
      "name": "SG Sonnenhof Grossaspach"
    },
    "v2y8m4zh9w9ql07": {
      "id": "v2y8m4zh9w9ql07",
      "name": "Dynamo Dresden"
    },
    "z318q66hdp1qo9j": {
      "id": "z318q66hdp1qo9j",
      "name": "MSV Duisburg"
    },
    "kn54qllh6lyqvy9": {
      "id": "kn54qllh6lyqvy9",
      "name": "SC Paderborn 07"
    },
    "jednm9wh1w6ryox": {
      "id": "jednm9wh1w6ryox",
      "name": "1. FC Magdeburg"
    },
    "kjw2r09hd99rz84": {
      "id": "kjw2r09hd99rz84",
      "name": "Arminia Bielefeld"
    },
    "z8yomo4ho2xq0j6": {
      "id": "z8yomo4ho2xq0j6",
      "name": "VFB Lubeck"
    },
    "z8yomo4hoglq0j6": {
      "id": "z8yomo4hoglq0j6",
      "name": "Rot Weiss Ahlen"
    },
    "v2y8m4zh9vlql07": {
      "id": "v2y8m4zh9vlql07",
      "name": "Fortuna Dusseldorf"
    },
    "vjxm8gh4p87r6od": {
      "id": "vjxm8gh4p87r6od",
      "name": "SV Babelsberg 03"
    },
    "jw2r09hllz9rz84": {
      "id": "jw2r09hllz9rz84",
      "name": "Kickers Emden"
    },
    "z8yomo4hop0q0j6": {
      "id": "z8yomo4hop0q0j6",
      "name": "SV Elversberg"
    },
    "kdj2ryoh379q1zp": {
      "id": "kdj2ryoh379q1zp",
      "name": "SpVgg Greuther Fürth"
    },
    "gy0or5jhkvwqwzv": {
      "id": "gy0or5jhkvwqwzv",
      "name": "FC St. Pauli"
    },
    "p3glrw7henvqdyj": {
      "id": "p3glrw7henvqdyj",
      "name": "Eintracht Frankfurt"
    },
    "4zp5rzghe4nq82w": {
      "id": "4zp5rzghe4nq82w",
      "name": "Borussia Dortmund"
    },
    "d23xmvkhze8qg8n": {
      "id": "d23xmvkhze8qg8n",
      "name": "Hansa Rostock"
    },
    "v2y8m4zhd2gql07": {
      "id": "v2y8m4zhd2gql07",
      "name": "FC Ingolstadt"
    },
    "kdj2ryoh3wyq1zp": {
      "id": "kdj2ryoh3wyq1zp",
      "name": "TSG Hoffenheim"
    },
    "gpxwrxlhw3nryk0": {
      "id": "gpxwrxlhw3nryk0",
      "name": "Hertha Berlin"
    },
    "gpxwrxlhwkvryk0": {
      "id": "gpxwrxlhwkvryk0",
      "name": "Schalke 04"
    },
    "l965mkyh9o4r1ge": {
      "id": "l965mkyh9o4r1ge",
      "name": "Borussia Monchengladbach"
    },
    "4zp5rzghewnq82w": {
      "id": "4zp5rzghewnq82w",
      "name": "Bayer 04 Leverkusen"
    },
    "z8yomo4hjwvq0j6": {
      "id": "z8yomo4hjwvq0j6",
      "name": "Eintracht Braunschweig"
    },
    "jednm9whl2kryox": {
      "id": "jednm9whl2kryox",
      "name": "1. FSV Mainz 05"
    },
    "4wyrn4h8xlpq86p": {
      "id": "4wyrn4h8xlpq86p",
      "name": "FC Oberneuland"
    },
    "p4jwq2ghdw7m0ve": {
      "id": "p4jwq2ghdw7m0ve",
      "name": "Rot-Weiss Oberhausen"
    },
    "9dn1m1ghd01moep": {
      "id": "9dn1m1ghd01moep",
      "name": "1. FC Nürnberg"
    },
    "z318q66hp2kqo9j": {
      "id": "z318q66hp2kqo9j",
      "name": "Karlsruher SC"
    }
  },
  "sport_events": {
    "1l4rjnhdv1wm7vx": {
      "id": "1l4rjnhdv1wm7vx",
      "home_team_id": "pxwrxlhg21kryk0",
      "away_team_id": "kdj2ryoh379q1zp",
      "start_timestamp": 1249221600,
      "status_id": 8,
      "sport_event_status": {
        "status_id": 8,
        "away_score": {
          "corners": 0,
          "red_card": 0,
          "yellow_card": 0,
          "penalty_score": 0,
          "regular_score": 0,
          "overTime_score": 1,
          "half_time_score": 0
        },
        "home_score": {
          "corners": 0,
          "red_card": 0,
          "yellow_card": 0,
          "penalty_score": 0,
          "regular_score": 0,
          "overTime_score": 0,
          "half_time_score": 0
        }
      },
      "related_id": "",
      "incidents": []
    },
    "1l4rjnhdv6wm7vx": {
      "id": "1l4rjnhdv6wm7vx",
      "home_team_id": "gpxwrxlho9xryk0",
      "away_team_id": "d23xmvkhze8qg8n",
      "start_timestamp": 1249065000,
      "status_id": 8,
      "sport_event_status": {
        "status_id": 8,
        "away_score": {
          "corners": 0,
          "red_card": 0,
          "yellow_card": 0,
          "penalty_score": 0,
          "regular_score": 1,
          "overTime_score": 0,
          "half_time_score": 0
        },
        "home_score": {
          "corners": 0,
          "red_card": 0,
          "yellow_card": 0,
          "penalty_score": 0,
          "regular_score": 2,
          "overTime_score": 0,
          "half_time_score": 0
        }
      },
      "related_id": "",
      "incidents": []
    },
    "23xmvkhl731qg8n": {
      "id": "23xmvkhl731qg8n",
      "home_team_id": "9k82rekh463repz",
      "away_team_id": "4zp5rzghewnq82w",
      "start_timestamp": 1253730600,
      "status_id": 8,
      "sport_event_status": {
        "status_id": 8,
        "away_score": {
          "corners": 0,
          "red_card": 0,
          "yellow_card": 0,
          "penalty_score": 0,
          "regular_score": 1,
          "overTime_score": 0,
          "half_time_score": 0
        },
        "home_score": {
          "corners": 0,
          "red_card": 0,
          "yellow_card": 0,
          "penalty_score": 0,
          "regular_score": 2,
          "overTime_score": 0,
          "half_time_score": 1
        }
      },
      "related_id": "",
      "incidents": []
    },
    "23xmvkhl7o1qg8n": {
      "id": "23xmvkhl7o1qg8n",
      "home_team_id": "jw2r09hlp31rz84",
      "away_team_id": "gy0or5jhkvwqwzv",
      "start_timestamp": 1249216200,
      "status_id": 8,
      "sport_event_status": {
        "status_id": 8,
        "away_score": {
          "corners": 0,
          "red_card": 0,
          "yellow_card": 0,
          "penalty_score": 0,
          "regular_score": 0,
          "overTime_score": 2,
          "half_time_score": 0
        },
        "home_score": {
          "corners": 0,
          "red_card": 0,
          "yellow_card": 0,
          "penalty_score": 0,
          "regular_score": 0,
          "overTime_score": 0,
          "half_time_score": 0
        }
      },
      "related_id": "",
      "incidents": []
    },
    "2y8m4zhel3pql07": {
      "id": "2y8m4zhel3pql07",
      "home_team_id": "z318q66hp2kqo9j",
      "away_team_id": "4zp5rzghe4nq82w",
      "start_timestamp": 1253644200,
      "status_id": 8,
      "sport_event_status": {
        "status_id": 8,
        "away_score": {
          "corners": 0,
          "red_card": 0,
          "yellow_card": 0,
          "penalty_score": 0,
          "regular_score": 3,
          "overTime_score": 0,
          "half_time_score": 2
        },
        "home_score": {
          "corners": 0,
          "red_card": 0,
          "yellow_card": 0,
          "penalty_score": 0,
          "regular_score": 0,
          "overTime_score": 0,
          "half_time_score": 0
        }
      },
      "related_id": "",
      "incidents": []
    },
    "2y8m4zhelgpql07": {
      "id": "2y8m4zhelgpql07",
      "home_team_id": "gpxwrxlho9xryk0",
      "away_team_id": "gpxwrxlhwkvryk0",
      "start_timestamp": 1265830200,
      "status_id": 8,
      "sport_event_status": {
        "status_id": 8,
        "away_score": {
          "corners": 0,
          "red_card": 0,
          "yellow_card": 0,
          "penalty_score": 0,
          "regular_score": 1,
          "overTime_score": 0,
          "half_time_score": 0
        },
        "home_score": {
          "corners": 0,
          "red_card": 0,
          "yellow_card": 0,
          "penalty_score": 0,
          "regular_score": 0,
          "overTime_score": 0,
          "half_time_score": 0
        }
      },
      "related_id": "",
      "incidents": []
    },
    "2y8m4zheljpql07": {
      "id": "2y8m4zheljpql07",
      "home_team_id": "jednm9wh1w6ryox",
      "away_team_id": "4zp5rzgheozq82w",
      "start_timestamp": 1249147800,
      "status_id": 8,
      "sport_event_status": {
        "status_id": 8,
        "away_score": {
          "corners": 0,
          "red_card": 0,
          "yellow_card": 0,
          "penalty_score": 0,
          "regular_score": 3,
          "overTime_score": 0,
          "half_time_score": 2
        },
        "home_score": {
          "corners": 0,
          "red_card": 0,
          "yellow_card": 0,
          "penalty_score": 0,
          "regular_score": 1,
          "overTime_score": 0,
          "half_time_score": 1
        }
      },
      "related_id": "",
      "incidents": []
    },
    "318q66h3l0vqo9j": {
      "id": "318q66h3l0vqo9j",
      "home_team_id": "1l4rjnh6p44m7vx",
      "away_team_id": "gx7lm7phd7em2wd",
      "start_timestamp": 1249133400,
      "status_id": 8,
      "sport_event_status": {
        "status_id": 8,
        "away_score": {
          "corners": 0,
          "red_card": 0,
          "yellow_card": 0,
          "penalty_score": 0,
          "regular_score": 4,
          "overTime_score": 0,
          "half_time_score": 0
        },
        "home_score": {
          "corners": 0,
          "red_card": 1,
          "yellow_card": 0,
          "penalty_score": 0,
          "regular_score": 1,
          "overTime_score": 0,
          "half_time_score": 1
        }
      },
      "related_id": "",
      "incidents": []
    },
    "318q66h3lvvqo9j": {
      "id": "318q66h3lvvqo9j",
      "home_team_id": "jw2r09hllz9rz84",
      "away_team_id": "yl5ergphj74r8k0",
      "start_timestamp": 1249133400,
      "status_id": 8,
      "sport_event_status": {
        "status_id": 8,
        "away_score": {
          "corners": 0,
          "red_card": 0,
          "yellow_card": 0,
          "penalty_score": 0,
          "regular_score": 3,
          "overTime_score": 0,
          "half_time_score": 1
        },
        "home_score": {
          "corners": 0,
          "red_card": 1,
          "yellow_card": 0,
          "penalty_score": 0,
          "regular_score": 0,
          "overTime_score": 0,
          "half_time_score": 0
        }
      },
      "related_id": "",
      "incidents": []
    },
    "3glrw7hgd14qdyj": {
      "id": "3glrw7hgd14qdyj",
      "home_team_id": "n54qllh2d1dqvy9",
      "away_team_id": "gpxwrxlhwkvryk0",
      "start_timestamp": 1249147800,
      "status_id": 8,
      "sport_event_status": {
        "status_id": 8,
        "away_score": {
          "corners": 0,
          "red_card": 0,
          "yellow_card": 0,
          "penalty_score": 0,
          "regular_score": 4,
          "overTime_score": 0,
          "half_time_score": 2
        },
        "home_score": {
          "corners": 0,
          "red_card": 0,
          "yellow_card": 0,
          "penalty_score": 0,
          "regular_score": 0,
          "overTime_score": 0,
          "half_time_score": 0
        }
      },
      "related_id": "",
      "incidents": []
    },
    "3glrw7hgdw4qdyj": {
      "id": "3glrw7hgdw4qdyj",
      "home_team_id": "vl7oqdehzvnr510",
      "away_team_id": "l965mkyh924r1ge",
      "start_timestamp": 1253725200,
      "status_id": 8,
      "sport_event_status": {
        "status_id": 8,
        "away_score": {
          "corners": 0,
          "red_card": 0,
          "yellow_card": 0,
          "penalty_score": 0,
          "regular_score": 0,
          "overTime_score": 0,
          "half_time_score": 0
        },
        "home_score": {
          "corners": 0,
          "red_card": 0,
          "yellow_card": 0,
          "penalty_score": 0,
          "regular_score": 1,
          "overTime_score": 0,
          "half_time_score": 0
        }
      },
      "related_id": "",
      "incidents": []
    },
    "4jwq2gh5l48m0ve": {
      "id": "4jwq2gh5l48m0ve",
      "home_team_id": "v2y8m4zhd2gql07",
      "away_team_id": "vl7oqdehzvnr510",
      "start_timestamp": 1249065000,
      "status_id": 8,
      "sport_event_status": {
        "status_id": 8,
        "away_score": {
          "corners": 0,
          "red_card": 0,
          "yellow_card": 0,
          "penalty_score": 0,
          "regular_score": 2,
          "overTime_score": 0,
          "half_time_score": 2
        },
        "home_score": {
          "corners": 0,
          "red_card": 0,
          "yellow_card": 0,
          "penalty_score": 0,
          "regular_score": 1,
          "overTime_score": 0,
          "half_time_score": 0
        }
      },
      "related_id": "",
      "incidents": []
    },
    "4jwq2gh5lk8m0ve": {
      "id": "4jwq2gh5lk8m0ve",
      "home_team_id": "gpxwrxlhojxryk0",
      "away_team_id": "p3glrw7henvqdyj",
      "start_timestamp": 1249227000,
      "status_id": 8,
      "sport_event_status": {
        "status_id": 8,
        "away_score": {
          "corners": 0,
          "red_card": 0,
          "yellow_card": 0,
          "penalty_score": 0,
          "regular_score": 3,
          "overTime_score": 0,
          "half_time_score": 0
        },
        "home_score": {
          "corners": 0,
          "red_card": 0,
          "yellow_card": 0,
          "penalty_score": 0,
          "regular_score": 0,
          "overTime_score": 0,
          "half_time_score": 0
        }
      },
      "related_id": "",
      "incidents": []
    },
    "4wyrn4h5g8vq86p": {
      "id": "4wyrn4h5g8vq86p",
      "home_team_id": "gy0or5jhkolqwzv",
      "away_team_id": "kjw2r09hd99rz84",
      "start_timestamp": 1253638800,
      "status_id": 8,
      "sport_event_status": {
        "status_id": 8,
        "away_score": {
          "corners": 0,
          "red_card": 0,
          "yellow_card": 0,
          "penalty_score": 0,
          "regular_score": 2,
          "overTime_score": 2,
          "half_time_score": 0
        },
        "home_score": {
          "corners": 0,
          "red_card": 0,
          "yellow_card": 0,
          "penalty_score": 0,
          "regular_score": 2,
          "overTime_score": 4,
          "half_time_score": 0
        }
      },
      "related_id": "",
      "incidents": []
    },
    "4wyrn4h5gdvq86p": {
      "id": "4wyrn4h5gdvq86p",
      "home_team_id": "9k82rekhdxorepz",
      "away_team_id": "vl7oqdehzvnr510",
      "start_timestamp": 1269372600,
      "status_id": 8,
      "sport_event_status": {
        "status_id": 8,
        "away_score": {
          "corners": 0,
          "red_card": 0,
          "yellow_card": 0,
          "penalty_score": 0,
          "regular_score": 0,
          "overTime_score": 0,
          "half_time_score": 0
        },
        "home_score": {
          "corners": 0,
          "red_card": 0,
          "yellow_card": 0,
          "penalty_score": 0,
          "regular_score": 2,
          "overTime_score": 0,
          "half_time_score": 1
        }
      },
      "related_id": "",
      "incidents": []
    },
    "4wyrn4h5gevq86p": {
      "id": "4wyrn4h5gevq86p",
      "home_team_id": "z8yomo4hop0q0j6",
      "away_team_id": "l965mkyh924r1ge",
      "start_timestamp": 1249133400,
      "status_id": 8,
      "sport_event_status": {
        "status_id": 8,
        "away_score": {
          "corners": 0,
          "red_card": 0,
          "yellow_card": 0,
          "penalty_score": 0,
          "regular_score": 2,
          "overTime_score": 0,
          "half_time_score": 1
        },
        "home_score": {
          "corners": 0,
          "red_card": 0,
          "yellow_card": 0,
          "penalty_score": 0,
          "regular_score": 0,
          "overTime_score": 0,
          "half_time_score": 0
        }
      },
      "related_id": "",
      "incidents": []
    },
    "6ypq3nhpx03md7o": {
      "id": "6ypq3nhpx03md7o",
      "home_team_id": "kn54qllhg3nqvy9",
      "away_team_id": "4zp5rzgheozq82w",
      "start_timestamp": 1253644200,
      "status_id": 8,
      "sport_event_status": {
        "status_id": 8,
        "away_score": {
          "corners": 0,
          "red_card": 0,
          "yellow_card": 0,
          "penalty_score": 0,
          "regular_score": 2,
          "overTime_score": 2,
          "half_time_score": 1
        },
        "home_score": {
          "corners": 0,
          "red_card": 0,
          "yellow_card": 0,
          "penalty_score": 0,
          "regular_score": 2,
          "overTime_score": 4,
          "half_time_score": 1
        }
      },
      "related_id": "",
      "incidents": []
    },
    "6ypq3nhpx53md7o": {
      "id": "6ypq3nhpx53md7o",
      "home_team_id": "jednm9whloeryox",
      "away_team_id": "z8yomo4hoglq0j6",
      "start_timestamp": 1249147800,
      "status_id": 8,
      "sport_event_status": {
        "status_id": 8,
        "away_score": {
          "corners": 0,
          "red_card": 0,
          "yellow_card": 0,
          "penalty_score": 5,
          "regular_score": 0,
          "overTime_score": 1,
          "half_time_score": 0
        },
        "home_score": {
          "corners": 0,
          "red_card": 0,
          "yellow_card": 0,
          "penalty_score": 4,
          "regular_score": 0,
          "overTime_score": 1,
          "half_time_score": 0
        }
      },
      "related_id": "",
      "incidents": []
    },
    "8yomo4h6n2gq0j6": {
      "id": "8yomo4h6n2gq0j6",
      "home_team_id": "9k82rekhdxorepz",
      "away_team_id": "yl5ergphjy2r8k0",
      "start_timestamp": 1273946400,
      "status_id": 8,
      "sport_event_status": {
        "status_id": 8,
        "away_score": {
          "corners": 0,
          "red_card": 0,
          "yellow_card": 2,
          "penalty_score": 0,
          "regular_score": 4,
          "overTime_score": 0,
          "half_time_score": 1
        },
        "home_score": {
          "corners": 0,
          "red_card": 1,
          "yellow_card": 4,
          "penalty_score": 0,
          "regular_score": 0,
          "overTime_score": 0,
          "half_time_score": 0
        }
      },
      "related_id": "",
      "incidents": []
    },
    "8yomo4h6n7gq0j6": {
      "id": "8yomo4h6n7gq0j6",
      "home_team_id": "kn54qllhy10qvy9",
      "away_team_id": "gpxwrxlhwkvryk0",
      "start_timestamp": 1253644200,
      "status_id": 8,
      "sport_event_status": {
        "status_id": 8,
        "away_score": {
          "corners": 0,
          "red_card": 0,
          "yellow_card": 0,
          "penalty_score": 0,
          "regular_score": 3,
          "overTime_score": 0,
          "half_time_score": 1
        },
        "home_score": {
          "corners": 0,
          "red_card": 0,
          "yellow_card": 0,
          "penalty_score": 0,
          "regular_score": 0,
          "overTime_score": 0,
          "half_time_score": 0
        }
      },
      "related_id": "",
      "incidents": []
    },
    "8yomo4h6nkgq0j6": {
      "id": "8yomo4h6nkgq0j6",
      "home_team_id": "y39mp1h3132mojx",
      "away_team_id": "z318q66hp2kqo9j",
      "start_timestamp": 1249147800,
      "status_id": 8,
      "sport_event_status": {
        "status_id": 8,
        "away_score": {
          "corners": 0,
          "red_card": 0,
          "yellow_card": 0,
          "penalty_score": 0,
          "regular_score": 2,
          "overTime_score": 0,
          "half_time_score": 1
        },
        "home_score": {
          "corners": 0,
          "red_card": 0,
          "yellow_card": 0,
          "penalty_score": 0,
          "regular_score": 0,
          "overTime_score": 0,
          "half_time_score": 0
        }
      },
      "related_id": "",
      "incidents": []
    },
    "965mkyh0p3lr1ge": {
      "id": "965mkyh0p3lr1ge",
      "home_team_id": "318q66howgdqo9j",
      "away_team_id": "kn54qllhy10qvy9",
      "start_timestamp": 1249227000,
      "status_id": 8,
      "sport_event_status": {
        "status_id": 8,
        "away_score": {
          "corners": 0,
          "red_card": 0,
          "yellow_card": 0,
          "penalty_score": 0,
          "regular_score": 1,
          "overTime_score": 0,
          "half_time_score": 0
        },
        "home_score": {
          "corners": 0,
          "red_card": 0,
          "yellow_card": 0,
          "penalty_score": 0,
          "regular_score": 0,
          "overTime_score": 0,
          "half_time_score": 0
        }
      },
      "related_id": "",
      "incidents": []
    },
    "965mkyh0p4lr1ge": {
      "id": "965mkyh0p4lr1ge",
      "home_team_id": "gpxwrxlho42ryk0",
      "away_team_id": "56ypq3nhdnkmd7o",
      "start_timestamp": 1249065000,
      "status_id": 8,
      "sport_event_status": {
        "status_id": 8,
        "away_score": {
          "corners": 0,
          "red_card": 0,
          "yellow_card": 0,
          "penalty_score": 0,
          "regular_score": 4,
          "overTime_score": 0,
          "half_time_score": 2
        },
        "home_score": {
          "corners": 0,
          "red_card": 0,
          "yellow_card": 0,
          "penalty_score": 0,
          "regular_score": 1,
          "overTime_score": 0,
          "half_time_score": 0
        }
      },
      "related_id": "",
      "incidents": []
    },
    "dj2ryoh98j4q1zp": {
      "id": "dj2ryoh98j4q1zp",
      "home_team_id": "vl7oqdehzvnr510",
      "away_team_id": "yl5ergphj74r8k0",
      "start_timestamp": 1265824800,
      "status_id": 8,
      "sport_event_status": {
        "status_id": 8,
        "away_score": {
          "corners": 0,
          "red_card": 3,
          "yellow_card": 0,
          "penalty_score": 0,
          "regular_score": 0,
          "overTime_score": 0,
          "half_time_score": 0
        },
        "home_score": {
          "corners": 0,
          "red_card": 0,
          "yellow_card": 0,
          "penalty_score": 0,
          "regular_score": 2,
          "overTime_score": 0,
          "half_time_score": 1
        }
      },
      "related_id": "",
      "incidents": []
    },
    "dj2ryoh98k4q1zp": {
      "id": "dj2ryoh98k4q1zp",
      "home_team_id": "z8yomo4hoglq0j6",
      "away_team_id": "kdj2ryoh379q1zp",
      "start_timestamp": 1253644200,
      "status_id": 8,
      "sport_event_status": {
        "status_id": 8,
        "away_score": {
          "corners": 0,
          "red_card": 0,
          "yellow_card": 0,
          "penalty_score": 0,
          "regular_score": 1,
          "overTime_score": 3,
          "half_time_score": 0
        },
        "home_score": {
          "corners": 0,
          "red_card": 0,
          "yellow_card": 0,
          "penalty_score": 0,
          "regular_score": 1,
          "overTime_score": 2,
          "half_time_score": 0
        }
      },
      "related_id": "",
      "incidents": []
    },
    "dj2ryoh98y4q1zp": {
      "id": "dj2ryoh98y4q1zp",
      "home_team_id": "kdj2ryoh0l3q1zp",
      "away_team_id": "kjw2r09hd99rz84",
      "start_timestamp": 1249133400,
      "status_id": 8,
      "sport_event_status": {
        "status_id": 8,
        "away_score": {
          "corners": 0,
          "red_card": 0,
          "yellow_card": 0,
          "penalty_score": 0,
          "regular_score": 3,
          "overTime_score": 0,
          "half_time_score": 2
        },
        "home_score": {
          "corners": 0,
          "red_card": 0,
          "yellow_card": 0,
          "penalty_score": 0,
          "regular_score": 0,
          "overTime_score": 0,
          "half_time_score": 0
        }
      },
      "related_id": "",
      "incidents": []
    },
    "dn1m1ghg6e3moep": {
      "id": "dn1m1ghg6e3moep",
      "home_team_id": "2y8m4zhj08lql07",
      "away_team_id": "4zp5rzghe4nq82w",
      "start_timestamp": 1249133400,
      "status_id": 8,
      "sport_event_status": {
        "status_id": 8,
        "away_score": {
          "corners": 0,
          "red_card": 0,
          "yellow_card": 0,
          "penalty_score": 0,
          "regular_score": 3,
          "overTime_score": 0,
          "half_time_score": 1
        },
        "home_score": {
          "corners": 0,
          "red_card": 1,
          "yellow_card": 0,
          "penalty_score": 0,
          "regular_score": 1,
          "overTime_score": 0,
          "half_time_score": 0
        }
      },
      "related_id": "",
      "incidents": []
    },
    "dn1m1ghg6n3moep": {
      "id": "dn1m1ghg6n3moep",
      "home_team_id": "3glrw7hwlnnqdyj",
      "away_team_id": "v2y8m4zh959ql07",
      "start_timestamp": 1249221600,
      "status_id": 8,
      "sport_event_status": {
        "status_id": 8,
        "away_score": {
          "corners": 0,
          "red_card": 0,
          "yellow_card": 0,
          "penalty_score": 0,
          "regular_score": 4,
          "overTime_score": 0,
          "half_time_score": 2
        },
        "home_score": {
          "corners": 0,
          "red_card": 0,
          "yellow_card": 0,
          "penalty_score": 0,
          "regular_score": 1,
          "overTime_score": 0,
          "half_time_score": 1
        }
      },
      "related_id": "",
      "incidents": []
    },
    "ednm9whp191ryox": {
      "id": "ednm9whp191ryox",
      "home_team_id": "gy0or5jhkolqwzv",
      "away_team_id": "kn54qllhylpqvy9",
      "start_timestamp": 1249227000,
      "status_id": 8,
      "sport_event_status": {
        "status_id": 8,
        "away_score": {
          "corners": 0,
          "red_card": 0,
          "yellow_card": 0,
          "penalty_score": 0,
          "regular_score": 1,
          "overTime_score": 0,
          "half_time_score": 1
        },
        "home_score": {
          "corners": 0,
          "red_card": 0,
          "yellow_card": 0,
          "penalty_score": 0,
          "regular_score": 3,
          "overTime_score": 0,
          "half_time_score": 0
        }
      },
      "related_id": "",
      "incidents": []
    },
    "ednm9whp1k1ryox": {
      "id": "ednm9whp1k1ryox",
      "home_team_id": "z8yomo4hjwvq0j6",
      "away_team_id": "9k82rekh463repz",
      "start_timestamp": 1249065000,
      "status_id": 8,
      "sport_event_status": {
        "status_id": 8,
        "away_score": {
          "corners": 0,
          "red_card": 1,
          "yellow_card": 0,
          "penalty_score": 0,
          "regular_score": 1,
          "overTime_score": 0,
          "half_time_score": 0
        },
        "home_score": {
          "corners": 0,
          "red_card": 0,
          "yellow_card": 0,
          "penalty_score": 0,
          "regular_score": 0,
          "overTime_score": 0,
          "half_time_score": 0
        }
      },
      "related_id": "",
      "incidents": []
    },
    "jw2r09hg8lprz84": {
      "id": "jw2r09hg8lprz84",
      "home_team_id": "yl5ergphjy2r8k0",
      "away_team_id": "p4jwq2ghdw7m0ve",
      "start_timestamp": 1253638800,
      "status_id": 8,
      "sport_event_status": {
        "status_id": 8,
        "away_score": {
          "corners": 0,
          "red_card": 0,
          "yellow_card": 0,
          "penalty_score": 0,
          "regular_score": 0,
          "overTime_score": 0,
          "half_time_score": 0
        },
        "home_score": {
          "corners": 0,
          "red_card": 0,
          "yellow_card": 0,
          "penalty_score": 0,
          "regular_score": 5,
          "overTime_score": 0,
          "half_time_score": 2
        }
      },
      "related_id": "",
      "incidents": []
    },
    "jw2r09hg8nprz84": {
      "id": "jw2r09hg8nprz84",
      "home_team_id": "kn54qllh6lyqvy9",
      "away_team_id": "z318q66hp7kqo9j",
      "start_timestamp": 1249133400,
      "status_id": 8,
      "sport_event_status": {
        "status_id": 8,
        "away_score": {
          "corners": 0,
          "red_card": 0,
          "yellow_card": 0,
          "penalty_score": 0,
          "regular_score": 1,
          "overTime_score": 0,
          "half_time_score": 1
        },
        "home_score": {
          "corners": 0,
          "red_card": 0,
          "yellow_card": 0,
          "penalty_score": 0,
          "regular_score": 0,
          "overTime_score": 0,
          "half_time_score": 0
        }
      },
      "related_id": "",
      "incidents": []
    },
    "jw2r09hg8xprz84": {
      "id": "jw2r09hg8xprz84",
      "home_team_id": "9k82rekhdxorepz",
      "away_team_id": "kdj2ryoh3wyq1zp",
      "start_timestamp": 1265743800,
      "status_id": 8,
      "sport_event_status": {
        "status_id": 8,
        "away_score": {
          "corners": 0,
          "red_card": 0,
          "yellow_card": 0,
          "penalty_score": 0,
          "regular_score": 1,
          "overTime_score": 0,
          "half_time_score": 0
        },
        "home_score": {
          "corners": 0,
          "red_card": 0,
          "yellow_card": 0,
          "penalty_score": 0,
          "regular_score": 2,
          "overTime_score": 0,
          "half_time_score": 1
        }
      },
      "related_id": "",
      "incidents": []
    },
    "k82rekhjl99repz": {
      "id": "k82rekhjl99repz",
      "home_team_id": "z8yomo4ho2xq0j6",
      "away_team_id": "jednm9whl2kryox",
      "start_timestamp": 1249065000,
      "status_id": 8,
      "sport_event_status": {
        "status_id": 8,
        "away_score": {
          "corners": 0,
          "red_card": 0,
          "yellow_card": 0,
          "penalty_score": 0,
          "regular_score": 1,
          "overTime_score": 1,
          "half_time_score": 1
        },
        "home_score": {
          "corners": 0,
          "red_card": 0,
          "yellow_card": 0,
          "penalty_score": 0,
          "regular_score": 1,
          "overTime_score": 2,
          "half_time_score": 0
        }
      },
      "related_id": "",
      "incidents": []
    },
    "k82rekhjly9repz": {
      "id": "k82rekhjly9repz",
      "home_team_id": "v2y8m4zh9vlql07",
      "away_team_id": "gy0or5jhdoyqwzv",
      "start_timestamp": 1249324500,
      "status_id": 8,
      "sport_event_status": {
        "status_id": 8,
        "away_score": {
          "corners": 0,
          "red_card": 0,
          "yellow_card": 0,
          "penalty_score": 4,
          "regular_score": 2,
          "overTime_score": 3,
          "half_time_score": 1
        },
        "home_score": {
          "corners": 0,
          "red_card": 0,
          "yellow_card": 0,
          "penalty_score": 1,
          "regular_score": 2,
          "overTime_score": 3,
          "half_time_score": 2
        }
      },
      "related_id": "",
      "incidents": []
    },
    "l5ergph7g3pr8k0": {
      "id": "l5ergph7g3pr8k0",
      "home_team_id": "v2y8m4zh9w9ql07",
      "away_team_id": "9dn1m1ghd01moep",
      "start_timestamp": 1249133400,
      "status_id": 8,
      "sport_event_status": {
        "status_id": 8,
        "away_score": {
          "corners": 0,
          "red_card": 0,
          "yellow_card": 0,
          "penalty_score": 0,
          "regular_score": 3,
          "overTime_score": 0,
          "half_time_score": 2
        },
        "home_score": {
          "corners": 0,
          "red_card": 0,
          "yellow_card": 0,
          "penalty_score": 0,
          "regular_score": 0,
          "overTime_score": 0,
          "half_time_score": 0
        }
      },
      "related_id": "",
      "incidents": []
    },
    "l5ergph7gopr8k0": {
      "id": "l5ergph7gopr8k0",
      "home_team_id": "9dn1m1ghd01moep",
      "away_team_id": "kdj2ryoh3wyq1zp",
      "start_timestamp": 1253638800,
      "status_id": 8,
      "sport_event_status": {
        "status_id": 8,
        "away_score": {
          "corners": 0,
          "red_card": 0,
          "yellow_card": 0,
          "penalty_score": 0,
          "regular_score": 1,
          "overTime_score": 0,
          "half_time_score": 1
        },
        "home_score": {
          "corners": 0,
          "red_card": 0,
          "yellow_card": 0,
          "penalty_score": 0,
          "regular_score": 0,
          "overTime_score": 0,
          "half_time_score": 0
        }
      },
      "related_id": "",
      "incidents": []
    },
    "l5ergph7gvpr8k0": {
      "id": "l5ergph7gvpr8k0",
      "home_team_id": "gpxwrxlhwkvryk0",
      "away_team_id": "yl5ergphjy2r8k0",
      "start_timestamp": 1269459000,
      "status_id": 8,
      "sport_event_status": {
        "status_id": 8,
        "away_score": {
          "corners": 0,
          "red_card": 0,
          "yellow_card": 0,
          "penalty_score": 0,
          "regular_score": 0,
          "overTime_score": 1,
          "half_time_score": 0
        },
        "home_score": {
          "corners": 0,
          "red_card": 0,
          "yellow_card": 0,
          "penalty_score": 0,
          "regular_score": 0,
          "overTime_score": 0,
          "half_time_score": 0
        }
      },
      "related_id": "",
      "incidents": []
    },
    "l7oqdeh974dr510": {
      "id": "l7oqdeh974dr510",
      "home_team_id": "yl5ergphjy2r8k0",
      "away_team_id": "kdj2ryoh379q1zp",
      "start_timestamp": 1265824800,
      "status_id": 8,
      "sport_event_status": {
        "status_id": 8,
        "away_score": {
          "corners": 0,
          "red_card": 0,
          "yellow_card": 0,
          "penalty_score": 0,
          "regular_score": 2,
          "overTime_score": 0,
          "half_time_score": 2
        },
        "home_score": {
          "corners": 0,
          "red_card": 0,
          "yellow_card": 0,
          "penalty_score": 0,
          "regular_score": 6,
          "overTime_score": 0,
          "half_time_score": 1
        }
      },
      "related_id": "",
      "incidents": []
    },
    "l7oqdeh976dr510": {
      "id": "l7oqdeh976dr510",
      "home_team_id": "9dn1m1ghz7omoep",
      "away_team_id": "l965mkyh9o4r1ge",
      "start_timestamp": 1249133400,
      "status_id": 8,
      "sport_event_status": {
        "status_id": 8,
        "away_score": {
          "corners": 0,
          "red_card": 0,
          "yellow_card": 0,
          "penalty_score": 0,
          "regular_score": 2,
          "overTime_score": 0,
          "half_time_score": 1
        },
        "home_score": {
          "corners": 0,
          "red_card": 1,
          "yellow_card": 0,
          "penalty_score": 0,
          "regular_score": 1,
          "overTime_score": 0,
          "half_time_score": 0
        }
      },
      "related_id": "",
      "incidents": []
    },
    "l7oqdeh97ndr510": {
      "id": "l7oqdeh97ndr510",
      "home_team_id": "l965mkyh9o4r1ge",
      "away_team_id": "z318q66hdp1qo9j",
      "start_timestamp": 1253638800,
      "status_id": 8,
      "sport_event_status": {
        "status_id": 8,
        "away_score": {
          "corners": 0,
          "red_card": 0,
          "yellow_card": 0,
          "penalty_score": 0,
          "regular_score": 1,
          "overTime_score": 0,
          "half_time_score": 0
        },
        "home_score": {
          "corners": 0,
          "red_card": 0,
          "yellow_card": 0,
          "penalty_score": 0,
          "regular_score": 0,
          "overTime_score": 0,
          "half_time_score": 0
        }
      },
      "related_id": "",
      "incidents": []
    },
    "n54qllhwv26qvy9": {
      "id": "n54qllhwv26qvy9",
      "home_team_id": "z8yomo4ho2xq0j6",
      "away_team_id": "gx7lm7phd7em2wd",
      "start_timestamp": 1253730600,
      "status_id": 8,
      "sport_event_status": {
        "status_id": 8,
        "away_score": {
          "corners": 0,
          "red_card": 0,
          "yellow_card": 0,
          "penalty_score": 0,
          "regular_score": 1,
          "overTime_score": 3,
          "half_time_score": 0
        },
        "home_score": {
          "corners": 0,
          "red_card": 0,
          "yellow_card": 0,
          "penalty_score": 0,
          "regular_score": 1,
          "overTime_score": 1,
          "half_time_score": 1
        }
      },
      "related_id": "",
      "incidents": []
    },
    "n54qllhwve6qvy9": {
      "id": "n54qllhwve6qvy9",
      "home_team_id": "9vjxm8gh613r6od",
      "away_team_id": "9k82rekhdxorepz",
      "start_timestamp": 1249216200,
      "status_id": 8,
      "sport_event_status": {
        "status_id": 8,
        "away_score": {
          "corners": 0,
          "red_card": 0,
          "yellow_card": 0,
          "penalty_score": 0,
          "regular_score": 5,
          "overTime_score": 0,
          "half_time_score": 3
        },
        "home_score": {
          "corners": 0,
          "red_card": 0,
          "yellow_card": 0,
          "penalty_score": 0,
          "regular_score": 0,
          "overTime_score": 0,
          "half_time_score": 0
        }
      },
      "related_id": "",
      "incidents": []
    },
    "pxwrxlh0d1yryk0": {
      "id": "pxwrxlh0d1yryk0",
      "home_team_id": "p3glrw7h580qdyj",
      "away_team_id": "gpxwrxlhw3nryk0",
      "start_timestamp": 1249147800,
      "status_id": 8,
      "sport_event_status": {
        "status_id": 8,
        "away_score": {
          "corners": 0,
          "red_card": 0,
          "yellow_card": 0,
          "penalty_score": 0,
          "regular_score": 1,
          "overTime_score": 3,
          "half_time_score": 1
        },
        "home_score": {
          "corners": 0,
          "red_card": 0,
          "yellow_card": 0,
          "penalty_score": 0,
          "regular_score": 1,
          "overTime_score": 1,
          "half_time_score": 0
        }
      },
      "related_id": "",
      "incidents": []
    },
    "pxwrxlh0dgyryk0": {
      "id": "pxwrxlh0dgyryk0",
      "home_team_id": "z318q66hp7kqo9j",
      "away_team_id": "gpxwrxlhw3nryk0",
      "start_timestamp": 1253725200,
      "status_id": 8,
      "sport_event_status": {
        "status_id": 8,
        "away_score": {
          "corners": 0,
          "red_card": 0,
          "yellow_card": 0,
          "penalty_score": 1,
          "regular_score": 2,
          "overTime_score": 2,
          "half_time_score": 0
        },
        "home_score": {
          "corners": 0,
          "red_card": 0,
          "yellow_card": 0,
          "penalty_score": 4,
          "regular_score": 2,
          "overTime_score": 2,
          "half_time_score": 1
        }
      },
      "related_id": "",
      "incidents": []
    },
    "vjxm8gh7y40r6od": {
      "id": "vjxm8gh7y40r6od",
      "home_team_id": "9k82rekhdxorepz",
      "away_team_id": "gy0or5jhkvwqwzv",
      "start_timestamp": 1253725200,
      "status_id": 8,
      "sport_event_status": {
        "status_id": 8,
        "away_score": {
          "corners": 0,
          "red_card": 0,
          "yellow_card": 0,
          "penalty_score": 0,
          "regular_score": 1,
          "overTime_score": 0,
          "half_time_score": 0
        },
        "home_score": {
          "corners": 0,
          "red_card": 0,
          "yellow_card": 0,
          "penalty_score": 0,
          "regular_score": 2,
          "overTime_score": 0,
          "half_time_score": 1
        }
      },
      "related_id": "",
      "incidents": []
    },
    "vjxm8gh7yg0r6od": {
      "id": "vjxm8gh7yg0r6od",
      "home_team_id": "ednm9whkd3zryox",
      "away_team_id": "kn54qllhg3nqvy9",
      "start_timestamp": 1249216200,
      "status_id": 8,
      "sport_event_status": {
        "status_id": 8,
        "away_score": {
          "corners": 0,
          "red_card": 0,
          "yellow_card": 0,
          "penalty_score": 0,
          "regular_score": 4,
          "overTime_score": 0,
          "half_time_score": 3
        },
        "home_score": {
          "corners": 0,
          "red_card": 0,
          "yellow_card": 0,
          "penalty_score": 0,
          "regular_score": 0,
          "overTime_score": 0,
          "half_time_score": 0
        }
      },
      "related_id": "",
      "incidents": []
    },
    "x7lm7ph24k2m2wd": {
      "id": "x7lm7ph24k2m2wd",
      "home_team_id": "p3glrw7henvqdyj",
      "away_team_id": "v2y8m4zh959ql07",
      "start_timestamp": 1253725200,
      "status_id": 8,
      "sport_event_status": {
        "status_id": 8,
        "away_score": {
          "corners": 0,
          "red_card": 0,
          "yellow_card": 0,
          "penalty_score": 0,
          "regular_score": 4,
          "overTime_score": 0,
          "half_time_score": 1
        },
        "home_score": {
          "corners": 0,
          "red_card": 0,
          "yellow_card": 0,
          "penalty_score": 0,
          "regular_score": 6,
          "overTime_score": 0,
          "half_time_score": 3
        }
      },
      "related_id": "",
      "incidents": []
    },
    "x7lm7ph24o2m2wd": {
      "id": "x7lm7ph24o2m2wd",
      "home_team_id": "l5ergphon6zr8k0",
      "away_team_id": "p4jwq2ghdw7m0ve",
      "start_timestamp": 1249216200,
      "status_id": 8,
      "sport_event_status": {
        "status_id": 8,
        "away_score": {
          "corners": 0,
          "red_card": 0,
          "yellow_card": 0,
          "penalty_score": 0,
          "regular_score": 3,
          "overTime_score": 0,
          "half_time_score": 1
        },
        "home_score": {
          "corners": 0,
          "red_card": 0,
          "yellow_card": 0,
          "penalty_score": 0,
          "regular_score": 0,
          "overTime_score": 0,
          "half_time_score": 0
        }
      },
      "related_id": "",
      "incidents": []
    },
    "y0or5jhw74dqwzv": {
      "id": "y0or5jhw74dqwzv",
      "home_team_id": "4wyrn4h8xlpq86p",
      "away_team_id": "kdj2ryoh3wyq1zp",
      "start_timestamp": 1249216200,
      "status_id": 8,
      "sport_event_status": {
        "status_id": 8,
        "away_score": {
          "corners": 0,
          "red_card": 0,
          "yellow_card": 0,
          "penalty_score": 0,
          "regular_score": 2,
          "overTime_score": 0,
          "half_time_score": 0
        },
        "home_score": {
          "corners": 0,
          "red_card": 0,
          "yellow_card": 0,
          "penalty_score": 0,
          "regular_score": 0,
          "overTime_score": 0,
          "half_time_score": 0
        }
      },
      "related_id": "",
      "incidents": []
    },
    "y0or5jhw7ldqwzv": {
      "id": "y0or5jhw7ldqwzv",
      "home_team_id": "gpxwrxlho9xryk0",
      "away_team_id": "gy0or5jhdoyqwzv",
      "start_timestamp": 1253730600,
      "status_id": 8,
      "sport_event_status": {
        "status_id": 8,
        "away_score": {
          "corners": 0,
          "red_card": 0,
          "yellow_card": 0,
          "penalty_score": 2,
          "regular_score": 2,
          "overTime_score": 3,
          "half_time_score": 0
        },
        "home_score": {
          "corners": 0,
          "red_card": 0,
          "yellow_card": 0,
          "penalty_score": 4,
          "regular_score": 2,
          "overTime_score": 3,
          "half_time_score": 0
        }
      },
      "related_id": "",
      "incidents": []
    },
    "y39mp1he753mojx": {
      "id": "y39mp1he753mojx",
      "home_team_id": "vjxm8gh4p87r6od",
      "away_team_id": "4zp5rzghewnq82w",
      "start_timestamp": 1249065000,
      "status_id": 8,
      "sport_event_status": {
        "status_id": 8,
        "away_score": {
          "corners": 0,
          "red_card": 0,
          "yellow_card": 0,
          "penalty_score": 0,
          "regular_score": 1,
          "overTime_score": 0,
          "half_time_score": 0
        },
        "home_score": {
          "corners": 0,
          "red_card": 0,
          "yellow_card": 0,
          "penalty_score": 0,
          "regular_score": 0,
          "overTime_score": 0,
          "half_time_score": 0
        }
      },
      "related_id": "",
      "incidents": []
    },
    "y39mp1he7j3mojx": {
      "id": "y39mp1he7j3mojx",
      "home_team_id": "n54qllh20zlqvy9",
      "away_team_id": "yl5ergphjy2r8k0",
      "start_timestamp": 1249227000,
      "status_id": 8,
      "sport_event_status": {
        "status_id": 8,
        "away_score": {
          "corners": 0,
          "red_card": 0,
          "yellow_card": 0,
          "penalty_score": 0,
          "regular_score": 3,
          "overTime_score": 0,
          "half_time_score": 0
        },
        "home_score": {
          "corners": 0,
          "red_card": 1,
          "yellow_card": 0,
          "penalty_score": 0,
          "regular_score": 1,
          "overTime_score": 0,
          "half_time_score": 0
        }
      },
      "related_id": "",
      "incidents": []
    },
    "zp5rzghd87kq82w": {
      "id": "zp5rzghd87kq82w",
      "home_team_id": "gpxwrxlhwy4ryk0",
      "away_team_id": "z318q66hdp1qo9j",
      "start_timestamp": 1249221600,
      "status_id": 8,
      "sport_event_status": {
        "status_id": 8,
        "away_score": {
          "corners": 0,
          "red_card": 0,
          "yellow_card": 0,
          "penalty_score": 0,
          "regular_score": 2,
          "overTime_score": 0,
          "half_time_score": 1
        },
        "home_score": {
          "corners": 0,
          "red_card": 0,
          "yellow_card": 0,
          "penalty_score": 0,
          "regular_score": 1,
          "overTime_score": 0,
          "half_time_score": 0
        }
      },
      "related_id": "",
      "incidents": []
    },
    "zp5rzghd8jkq82w": {
      "id": "zp5rzghd8jkq82w",
      "home_team_id": "yl5ergphj74r8k0",
      "away_team_id": "56ypq3nhdnkmd7o",
      "start_timestamp": 1253730600,
      "status_id": 8,
      "sport_event_status": {
        "status_id": 8,
        "away_score": {
          "corners": 0,
          "red_card": 1,
          "yellow_card": 0,
          "penalty_score": 0,
          "regular_score": 2,
          "overTime_score": 0,
          "half_time_score": 0
        },
        "home_score": {
          "corners": 0,
          "red_card": 0,
          "yellow_card": 0,
          "penalty_score": 0,
          "regular_score": 3,
          "overTime_score": 0,
          "half_time_score": 2
        }
      },
      "related_id": "",
      "incidents": []
    }
  }
}