{
  "season_id": "gy0or5jhp77qwzv",
  "brackets": [
    {
      "id": "318q66h05x0qo9j",
      "competition_id": "e4wyrn4hnxq86pv",
      "season_id": "gy0or5jhp77qwzv",
      "name": "Knockout Stage",
      "abbr": "Knockout Stage",
      "start_time": 1709827200,
      "end_time": 1712591940,
      "rounds": [
        {
          "id": "6ypq3nhekxgmd7o",
          "bracket_id": "318q66h05x0qo9j",
          "name": "Quarterfinals",
          "abbr": "QF",
          "start_time": 1709935200,
          "end_time": 1710106200,
          "number": 1,
          "match_ups": [
            {
              "id": "2y8m4zhjg82kql0",
              "round_id": "6ypq3nhekxgmd7o",
              "number": 1,
              "type_id": 1,
              "state_id": 8,
              "home_team_id": "965mkyh49yer1ge",
              "away_team_id": "pxwrxlh10l0ryk0",
              "winner_team_id": "pxwrxlh10l0ryk0",
              "home_score": 0,
              "away_score": 4,
              "parent_ids": [
                "k82rekh9y880rep"
              ],
              "children_ids": [],
              "event_ids": [
                "jw2r09h27j9jrz8"
              ]
            },
            {
              "id": "8yomo4hk2vwwq0j",
              "round_id": "6ypq3nhekxgmd7o",
              "number": 2,
              "type_id": 1,
              "state_id": 7,
              "home_team_id": "6ypq3nh5n1zmd7o",
              "away_team_id": "jw2r09hx362rz84",
              "winner_team_id": "6ypq3nh5n1zmd7o",
              "home_score": 3,
              "away_score": 0,
              "parent_ids": [
                "k82rekh9y880rep"
              ],
              "children_ids": [],
              "event_ids": [
                "dj2ryoh15g42q1z"
              ]
            },
            {
              "id": "6ypq3nh5zw2xmd7",
              "round_id": "6ypq3nhekxgmd7o",
              "number": 3,
              "type_id": 1,
              "state_id": 7,
              "home_team_id": "23xmvkh3kj0qg8n",
              "away_team_id": "ednm9whkod9ryox",
              "winner_team_id": "23xmvkh3kj0qg8n",
              "home_score": 1,
              "away_score": 0,
              "parent_ids": [
                "318q66h0v77wqo9"
              ],
              "children_ids": [],
              "event_ids": [
                "l7oqdehod02lr51"
              ]
            },
            {
              "id": "pxwrxlh19jdpryk",
              "round_id": "6ypq3nhekxgmd7o",
              "number": 4,
              "type_id": 1,
              "state_id": 7,
              "home_team_id": "x7lm7phoeo2m2wd",
              "away_team_id": "vjxm8ghg9x6r6od",
              "winner_team_id": "x7lm7phoeo2m2wd",
              "home_score": 2,
              "away_score": 0,
              "parent_ids": [
                "318q66h0v77wqo9"
              ],
              "children_ids": [],
              "event_ids": [
                "l5ergphw2eyvr8k"
              ]
            }
          ]
        },
        {
          "id": "pxwrxlhelderyk0",
          "bracket_id": "318q66h05x0qo9j",
          "name": "Semi Finals",
          "abbr": "SF",
          "start_time": 1710617400,
          "end_time": 1711497600,
          "number": 2,
          "match_ups": [
            {
              "id": "k82rekh9y880rep",
              "round_id": "pxwrxlhelderyk0",
              "number": 1,
              "type_id": 5,
              "state_id": 7,
              "home_team_id": "pxwrxlh10l0ryk0",
              "away_team_id": "6ypq3nh5n1zmd7o",
              "winner_team_id": "pxwrxlh10l0ryk0",
              "home_score": 7,
              "away_score": 6,
              "parent_ids": [
                "1l4rjnh1z09nm7v"
              ],
              "children_ids": [
                "2y8m4zhjg82kql0",
                "8yomo4hk2vwwq0j"
              ],
              "event_ids": [
                "6ypq3nh3gv6ymd7",
                "4jwq2ghe6ww6m0v"
              ]
            },
            {
              "id": "318q66h0v77wqo9",
              "round_id": "pxwrxlhelderyk0",
              "number": 2,
              "type_id": 5,
              "state_id": 8,
              "home_team_id": "23xmvkh3kj0qg8n",
              "away_team_id": "x7lm7phoeo2m2wd",
              "winner_team_id": "x7lm7phoeo2m2wd",
              "home_score": 3,
              "away_score": 5,
              "parent_ids": [
                "1l4rjnh1z09nm7v"
              ],
              "children_ids": [
                "6ypq3nh5zw2xmd7",
                "pxwrxlh19jdpryk"
              ],
              "event_ids": [
                "8yomo4h391eoq0j",
                "1l4rjnh42gg3m7v"
              ]
            }
          ]
        },
        {
          "id": "3glrw7h64dpqdyj",
          "bracket_id": "318q66h05x0qo9j",
          "name": "Final",
          "abbr": "F",
          "start_time": 1711827000,
          "end_time": 1712431800,
          "number": 3,
          "match_ups": [
            {
              "id": "1l4rjnh1z09nm7v",
              "round_id": "3glrw7h64dpqdyj",
              "number": 1,
              "type_id": 5,
              "state_id": 8,
              "home_team_id": "pxwrxlh10l0ryk0",
              "away_team_id": "x7lm7phoeo2m2wd",
              "winner_team_id": "x7lm7phoeo2m2wd",
              "home_score": 1,
              "away_score": 3,
              "parent_ids": [],
              "children_ids": [
                "k82rekh9y880rep",
                "318q66h0v77wqo9"
              ],
              "event_ids": [
                "1l4rjnh451kom7v",
                "4jwq2ghepk72m0v"
              ]
            }
          ]
        }
      ]
    }
  ],
  "competitors": {
    "vjxm8ghg9x6r6od": {
      "id": "vjxm8ghg9x6r6od",
      "name": "Brasil de Pelotas"
    },
    "23xmvkh3kj0qg8n": {
      "id": "23xmvkh3kj0qg8n",
      "name": "Caxias RS"
    },
    "965mkyh49yer1ge": {
      "id": "965mkyh49yer1ge",
      "name": "Guarany de Bage"
    },
    "6ypq3nh5n1zmd7o": {
      "id": "6ypq3nh5n1zmd7o",
      "name": "Internacional (RS) B"
    },
    "x7lm7phoeo2m2wd": {
      "id": "x7lm7phoeo2m2wd",
      "name": "Gremio B"
    },
    "jw2r09hx362rz84": {
      "id": "jw2r09hx362rz84",
      "name": "São Luiz"
    },
    "ednm9whkod9ryox": {
      "id": "ednm9whkod9ryox",
      "name": "Esporte Clube São José Porto Alegre"
    },
    "pxwrxlh10l0ryk0": {
      "id": "pxwrxlh10l0ryk0",
      "name": "EC Juventude II"
    }
  },
  "sport_events": {
    "1l4rjnh42gg3m7v": {
      "id": "1l4rjnh42gg3m7v",
      "home_team_id": "p4jwq2ghdd9m0ve",
      "away_team_id": "23xmvkh3kj0qg8n",
      "start_timestamp": 1711497600,
      "status_id": 8,
      "sport_event_status": {
        "status_id": 8,
        "away_score": {
          "corners": 11,
          "red_card": 0,
          "yellow_card": 4,
          "penalty_score": 0,
          "regular_score": 2,
          "overTime_score": 0,
          "half_time_score": 0
        },
        "home_score": {
          "corners": 2,
          "red_card": 1,
          "yellow_card": 1,
          "penalty_score": 0,
          "regular_score": 3,
          "overTime_score": 0,
          "half_time_score": 3
        },
        "kick_of_timestamp": 0
      },
      "related_id": "",
      "incidents": [
        {
          "time": 21,
          "type": 1,
          "position": 1,
          "player_id": "jw2r09hllpvrz84",
          "away_score": 0,
          "home_score": 1,
          "player_name": "Diego Costa"
        },
        {
          "time": 27,
          "type": 3,
          "position": 2,
          "player_id": "x7lm7ph0d1k6m2w",
          "player_name": "Elyeser"
        },
        {
          "time": 29,
          "type": 1,
          "position": 1,
          "player_id": "1l4rjnhzvgwm7vx",
          "away_score": 0,
          "home_score": 2,
          "player_name": "Franco Cristaldo"
        },
        {
          "time": 39,
          "type": 1,
          "position": 1,
          "player_id": "jw2r09hllpvrz84",
          "away_score": 0,
          "home_score": 3,
          "player_name": "Diego Costa"
        },
        {
          "time": 43,
          "type": 9,
          "position": 1,
          "in_player_id": "n54qllh8lyg2qvy",
          "out_player_id": "4jwq2ghv6zdpm0v",
          "in_player_name": "Queiroz du",
          "out_player_name": "Pepê"
        },
        {
          "time": 48,
          "type": 4,
          "position": 1,
          "player_id": "l7oqdeh4ee4pr51",
          "player_name": "Mayk·Van Van"
        },
        {
          "time": 45,
          "type": 11,
          "position": 0
        },
        {
          "time": 46,
          "type": 9,
          "position": 1,
          "in_player_id": "l7oqdehl138yr51",
          "out_player_id": "1l4rjnhzvgwm7vx",
          "in_player_name": "costa wesley",
          "out_player_name": "Franco Cristaldo"
        },
        {
          "time": 46,
          "type": 9,
          "position": 2,
          "in_player_id": "zp5rzgh1vddq82w",
          "out_player_id": "23xmvkhkn7v1qg8",
          "in_player_name": "Vitor Feijão",
          "out_player_name": "Martins emerson"
        },
        {
          "time": 46,
          "type": 9,
          "position": 2,
          "in_player_id": "4wyrn4hv92k9q86",
          "out_player_id": "zp5rzghp6wk1q82",
          "in_player_name": "vinicius joel",
          "out_player_name": "Alvaro"
        },
        {
          "time": 50,
          "type": 3,
          "position": 2,
          "player_id": "zp5rzgh1vddq82w",
          "player_name": "Vitor Feijão"
        },
        {
          "time": 53,
          "type": 3,
          "position": 2,
          "player_id": "2y8m4zhgzo4wql0",
          "player_name": "Jean Pierre Freitas Militão"
        },
        {
          "time": 58,
          "type": 1,
          "position": 2,
          "player_id": "zp5rzgh1vddq82w",
          "away_score": 1,
          "home_score": 3,
          "player_name": "Vitor Feijão"
        },
        {
          "time": 59,
          "type": 9,
          "position": 1,
          "in_player_id": "2y8m4zhz1n90ql0",
          "out_player_id": "jw2r09hllpvrz84",
          "in_player_name": "henrique andre",
          "out_player_name": "Diego Costa"
        },
        {
          "time": 64,
          "type": 9,
          "position": 2,
          "in_player_id": "l7oqdeh4kpvpr51",
          "out_player_id": "dn1m1gh368yxmoe",
          "in_player_name": "Robinho",
          "out_player_name": "Silva gabriel"
        },
        {
          "time": 69,
          "type": 3,
          "position": 2,
          "player_id": "l7oqdeh4kpvpr51",
          "player_name": "Robinho"
        },
        {
          "time": 72,
          "type": 3,
          "position": 1
        },
        {
          "time": 73,
          "type": 9,
          "position": 1,
          "in_player_id": "4jwq2ghx06km0ve",
          "out_player_id": "k82rekh31jnkrep",
          "in_player_name": "Yeferson Soteldo",
          "out_player_name": "nunes gustavo"
        },
        {
          "time": 73,
          "type": 9,
          "position": 1,
          "in_player_id": "dn1m1ghoxkkmoep",
          "out_player_id": "pxwrxlh9o66ryk0",
          "in_player_name": "Douglas Moreira Fagundes",
          "out_player_name": "Cristian Pavón"
        },
        {
          "time": 74,
          "type": 9,
          "position": 2,
          "in_player_id": "jw2r09hw19o7rz8",
          "out_player_id": "x7lm7ph0d1k6m2w",
          "in_player_name": "lustosa david",
          "out_player_name": "Elyeser"
        },
        {
          "time": 74,
          "type": 9,
          "position": 2,
          "in_player_id": "l7oqdeh4kd2nr51",
          "out_player_id": "2y8m4zhgzo4wql0",
          "in_player_name": "Rocha matheus",
          "out_player_name": "Jean Pierre Freitas Militão"
        },
        {
          "time": 81,
          "type": 1,
          "position": 2,
          "player_id": "4wyrn4hv81lxq86",
          "away_score": 2,
          "home_score": 3,
          "player_name": "Bastos Tomas"
        },
        {
          "time": 89,
          "type": 3,
          "position": 1,
          "player_id": "dn1m1gh3nd6moep",
          "player_name": "João Pedro"
        },
        {
          "time": 93,
          "type": 3,
          "position": 2
        },
        {
          "time": 90,
          "type": 12,
          "position": 0
        }
      ]
    },
    "1l4rjnh451kom7v": {
      "id": "1l4rjnh451kom7v",
      "home_team_id": "gpxwrxlhoe0ryk0",
      "away_team_id": "p4jwq2ghdd9m0ve",
      "start_timestamp": 1711827000,
      "status_id": 8,
      "sport_event_status": {
        "status_id": 8,
        "away_score": {
          "corners": 1,
          "red_card": 0,
          "yellow_card": 3,
          "penalty_score": 0,
          "regular_score": 0,
          "overTime_score": 0,
          "half_time_score": 0
        },
        "home_score": {
          "corners": 10,
          "red_card": 0,
          "yellow_card": 5,
          "penalty_score": 0,
          "regular_score": 0,
          "overTime_score": 0,
          "half_time_score": 0
        }
      },
      "related_id": "",
      "incidents": [
        {
          "time": 34,
          "type": 9,
          "position": 1,
          "in_player_id": "318q66h4zwn3qo9",
          "out_player_id": "l7oqdeh4v7kdr51",
          "in_player_name": "Rildo Goncalves de Amorin Filho",
          "out_player_name": "Edson Guilherme Mendes dos Santos"
        },
        {
          "time": 45,
          "type": 11,
          "position": 0
        },
        {
          "time": 51,
          "type": 3,
          "position": 1,
          "player_id": "k82rekhyy0yrepz",
          "player_name": "Jadson Alves dos Santos"
        },
        {
          "time": 55,
          "type": 3,
          "position": 2,
          "player_id": "8yomo4h791gq0j6",
          "player_name": "Fábio Da Silva"
        },
        {
          "time": 58,
          "type": 3,
          "position": 2,
          "player_id": "dn1m1gh8100jmoe",
          "player_name": "pedro joao"
        },
        {
          "time": 59,
          "type": 3,
          "position": 2,
          "player_id": "k82rekhy3zzrepz",
          "player_name": "Walter Kannemann"
        },
        {
          "time": 63,
          "type": 9,
          "position": 2,
          "in_player_id": "n54qllh8lyg2qvy",
          "out_player_id": "1l4rjnhzvgwm7vx",
          "in_player_name": "Queiroz du",
          "out_player_name": "Franco Cristaldo"
        },
        {
          "time": 63,
          "type": 9,
          "position": 2,
          "in_player_id": "dn1m1ghoxkkmoep",
          "out_player_id": "4jwq2ghv6zdpm0v",
          "in_player_name": "Douglas Moreira Fagundes",
          "out_player_name": "Pepê"
        },
        {
          "time": 65,
          "type": 3,
          "position": 1,
          "player_id": "318q66h4zwn3qo9",
          "player_name": "Rildo Goncalves de Amorin Filho"
        },
        {
          "time": 70,
          "type": 3,
          "position": 1,
          "player_id": "dj2ryoh2y6nq1zp",
          "player_name": "Jean Carlos"
        },
        {
          "time": 74,
          "type": 3,
          "position": 1,
          "player_id": "4wyrn4hdl4vpq86",
          "player_name": "João Lucas"
        },
        {
          "time": 77,
          "type": 9,
          "position": 1,
          "in_player_id": "zp5rzghp2zw0q82",
          "out_player_id": "l5ergph3jgor8k0",
          "in_player_name": "Erick Samuel Corrêa Farias",
          "out_player_name": "Gilberto"
        },
        {
          "time": 77,
          "type": 9,
          "position": 1,
          "in_player_id": "jw2r09hpx7prz84",
          "out_player_id": "dj2ryoh2y6nq1zp",
          "in_player_name": "Nenê",
          "out_player_name": "Jean Carlos"
        },
        {
          "time": 78,
          "type": 9,
          "position": 2,
          "in_player_id": "4jwq2ghx06km0ve",
          "out_player_id": "pxwrxlh9o66ryk0",
          "in_player_name": "Yeferson Soteldo",
          "out_player_name": "Cristian Pavón"
        },
        {
          "time": 79,
          "type": 3,
          "position": 1,
          "player_id": "k82rekhy4n6prep",
          "player_name": "Sam rodrigo"
        },
        {
          "time": 86,
          "type": 9,
          "position": 2,
          "in_player_id": "dn1m1gh8100jmoe",
          "out_player_id": "jw2r09hllpvrz84",
          "in_player_name": "pedro joao",
          "out_player_name": "Diego Costa"
        },
        {
          "time": 86,
          "type": 9,
          "position": 2,
          "in_player_id": "k82rekhy4p1repz",
          "out_player_id": "k82rekh31jnkrep",
          "in_player_name": "Nathan",
          "out_player_name": "nunes gustavo"
        },
        {
          "time": 90,
          "type": 9,
          "position": 1,
          "in_player_id": "jw2r09hxdl7xrz8",
          "out_player_id": "zp5rzghpy27zq82",
          "in_player_name": "Kleiton·Pego Duarte",
          "out_player_name": "Lucas Henrique Barbosa"
        },
        {
          "time": 90,
          "type": 12,
          "position": 0
        }
      ]
    },
    "4jwq2ghe6ww6m0v": {
      "id": "4jwq2ghe6ww6m0v",
      "home_team_id": "l965mkyhxxxr1ge",
      "away_team_id": "gpxwrxlhoe0ryk0",
      "start_timestamp": 1711413900,
      "status_id": 8,
      "sport_event_status": {
        "status_id": 8,
        "away_score": {
          "corners": 3,
          "red_card": 0,
          "yellow_card": 4,
          "penalty_score": 6,
          "regular_score": 1,
          "overTime_score": 0,
          "half_time_score": 1
        },
        "home_score": {
          "corners": 6,
          "red_card": 1,
          "yellow_card": 1,
          "penalty_score": 5,
          "regular_score": 1,
          "overTime_score": 0,
          "half_time_score": 0
        }
      },
      "related_id": "",
      "incidents": [
        {
          "time": 13,
          "type": 9,
          "position": 2,
          "in_player_id": "23xmvkh4xxoxqg8",
          "out_player_id": "4jwq2ghvje07m0v",
          "in_player_name": "Para",
          "out_player_name": "Danilo Boza Junior"
        },
        {
          "time": 18,
          "type": 3,
          "position": 2,
          "player_id": "k82rekhy4n6prep",
          "player_name": "Sam rodrigo"
        },
        {
          "time": 25,
          "type": 3,
          "position": 2,
          "player_id": "vjxm8gh2271r6od",
          "player_name": "Ze Marcos"
        },
        {
          "time": 31,
          "type": 1,
          "position": 2,
          "player_id": "vjxm8gh2271r6od",
          "away_score": 1,
          "home_score": 0,
          "player_name": "Ze Marcos"
        },
        {
          "time": 45,
          "type": 11,
          "position": 0
        },
        {
          "time": 46,
          "type": 9,
          "position": 1,
          "in_player_id": "l7oqdehl12v2r51",
          "out_player_id": "x7lm7ph9pno7m2w",
          "in_player_name": "valencia enner",
          "out_player_name": "henrique bruno"
        },
        {
          "time": 55,
          "type": 1,
          "position": 1,
          "player_id": "n54qllhxxd4qvy9",
          "away_score": 1,
          "home_score": 1,
          "player_name": "Renê"
        },
        {
          "time": 69,
          "type": 9,
          "position": 2,
          "in_player_id": "318q66h4zwn3qo9",
          "out_player_id": "l7oqdeh4v7kdr51",
          "in_player_name": "Rildo Goncalves de Amorin Filho",
          "out_player_name": "Edson Guilherme Mendes dos Santos"
        },
        {
          "time": 69,
          "type": 9,
          "position": 2,
          "in_player_id": "jw2r09hpx7prz84",
          "out_player_id": "dj2ryoh2y6nq1zp",
          "in_player_name": "Nenê",
          "out_player_name": "Jean Carlos"
        },
        {
          "time": 76,
          "type": 3,
          "position": 2,
          "player_id": "jw2r09hpx7prz84",
          "player_name": "Nenê"
        },
        {
          "time": 77,
          "type": 4,
          "position": 1,
          "player_id": "8yomo4h2gkkkq0j",
          "player_name": "Mauricio Magalhães Prado"
        },
        {
          "time": 78,
          "type": 9,
          "position": 1,
          "in_player_id": "zp5rzghz6ly8q82",
          "out_player_id": "k82rekho2d8erep",
          "in_player_name": "Romulo",
          "out_player_name": "Lucca"
        },
        {
          "time": 82,
          "type": 9,
          "position": 2,
          "in_player_id": "jw2r09hxdl7xrz8",
          "out_player_id": "zp5rzghpy27zq82",
          "in_player_name": "Kleiton·Pego Duarte",
          "out_player_name": "Lucas Henrique Barbosa"
        },
        {
          "time": 82,
          "type": 9,
          "position": 2,
          "in_player_id": "318q66hjk2l4qo9",
          "out_player_id": "23xmvkh4xxoxqg8",
          "in_player_name": "gomes kelvi",
          "out_player_name": "Para"
        },
        {
          "time": 85,
          "type": 9,
          "position": 1,
          "in_player_id": "k82rekhyw008rep",
          "out_player_id": "l965mkyhpvdr1ge",
          "in_player_name": "Bruno Gomes",
          "out_player_name": "Charles Aránguiz"
        },
        {
          "time": 90,
          "type": 3,
          "position": 1,
          "player_id": "y0or5jh4j1pqwzv",
          "player_name": "Gabriel Mercado"
        },
        {
          "time": 90,
          "type": 3,
          "position": 2,
          "player_id": "jw2r09hw1987rz8",
          "player_name": "goncalves caique"
        },
        {
          "time": 95,
          "type": 9,
          "position": 1,
          "in_player_id": "dj2ryohg7vo5q1z",
          "out_player_id": "pxwrxlh2no7ryk0",
          "in_player_name": "Robert Renan Alves Barbosa",
          "out_player_name": "Vitão"
        },
        {
          "time": 90,
          "type": 12,
          "position": 0
        },
        {
          "time": 90,
          "type": 29,
          "position": 1,
          "player_id": "n54qllhek83qvy9",
          "away_score": 0,
          "home_score": 1,
          "player_name": "Alan Patrick"
        },
        {
          "time": 90,
          "type": 29,
          "position": 2,
          "player_id": "l5ergph3jgor8k0",
          "away_score": 1,
          "home_score": 1,
          "player_name": "Gilberto"
        },
        {
          "time": 90,
          "type": 29,
          "position": 1,
          "player_id": "n54qllhxxd4qvy9",
          "away_score": 1,
          "home_score": 2,
          "player_name": "Renê"
        },
        {
          "time": 90,
          "type": 30,
          "position": 2,
          "player_id": "23xmvkhden7qg8n",
          "away_score": 1,
          "home_score": 2,
          "player_name": "Alan Luciano Ruschel"
        },
        {
          "time": 90,
          "type": 30,
          "position": 1,
          "player_id": "y0or5jh4j1pqwzv",
          "away_score": 1,
          "home_score": 2,
          "player_name": "Gabriel Mercado"
        },
        {
          "time": 90,
          "type": 29,
          "position": 2,
          "player_id": "318q66h4zwn3qo9",
          "away_score": 2,
          "home_score": 2,
          "player_name": "Rildo Goncalves de Amorin Filho"
        },
        {
          "time": 90,
          "type": 29,
          "position": 1,
          "player_id": "2y8m4zhg8x6ql07",
          "away_score": 2,
          "home_score": 3,
          "player_name": "Wanderson"
        },
        {
          "time": 90,
          "type": 29,
          "position": 2,
          "player_id": "k82rekhyy0yrepz",
          "away_score": 3,
          "home_score": 3,
          "player_name": "Jadson Alves dos Santos"
        },
        {
          "time": 90,
          "type": 29,
          "position": 1,
          "player_id": "l7oqdehl12v2r51",
          "away_score": 3,
          "home_score": 4,
          "player_name": "valencia enner"
        },
        {
          "time": 90,
          "type": 29,
          "position": 2,
          "player_id": "jw2r09hpx7prz84",
          "away_score": 4,
          "home_score": 4,
          "player_name": "Nenê"
        },
        {
          "time": 90,
          "type": 29,
          "position": 1,
          "player_id": "k82rekhyw008rep",
          "away_score": 4,
          "home_score": 5,
          "player_name": "Bruno Gomes"
        },
        {
          "time": 90,
          "type": 29,
          "position": 2,
          "player_id": "jw2r09hxdl7xrz8",
          "away_score": 5,
          "home_score": 5,
          "player_name": "Kleiton·Pego Duarte"
        },
        {
          "time": 90,
          "type": 30,
          "position": 1,
          "player_id": "dj2ryohg7vo5q1z",
          "away_score": 5,
          "home_score": 5,
          "player_name": "Robert Renan Alves Barbosa"
        },
        {
          "time": 90,
          "type": 29,
          "position": 2,
          "player_id": "318q66hjk2l4qo9",
          "away_score": 6,
          "home_score": 5,
          "player_name": "gomes kelvi"
        },
        {
          "time": 120,
          "type": 27,
          "position": 0
        }
      ]
    },
    "4jwq2ghepk72m0v": {
      "id": "4jwq2ghepk72m0v",
      "home_team_id": "p4jwq2ghdd9m0ve",
      "away_team_id": "gpxwrxlhoe0ryk0",
      "start_timestamp": 1712431800,
      "status_id": 8,
      "sport_event_status": {
        "status_id": 8,
        "away_score": {
          "corners": 2,
          "red_card": 0,
          "yellow_card": 6,
          "penalty_score": 0,
          "regular_score": 1,
          "overTime_score": 0,
          "half_time_score": 1
        },
        "home_score": {
          "corners": 4,
          "red_card": 0,
          "yellow_card": 3,
          "penalty_score": 0,
          "regular_score": 3,
          "overTime_score": 0,
          "half_time_score": 2
        }
      },
      "related_id": "",
      "incidents": [
        {
          "time": 5,
          "type": 1,
          "position": 2,
          "player_id": "l5ergph3jgor8k0",
          "away_score": 1,
          "home_score": 0,
          "player_name": "Gilberto"
        },
        {
          "time": 24,
          "type": 3,
          "position": 2,
          "player_id": "k82rekhyy0yrepz",
          "player_name": "Jadson Alves dos Santos"
        },
        {
          "time": 42,
          "type": 1,
          "position": 1,
          "player_id": "1l4rjnhzvgwm7vx",
          "away_score": 1,
          "home_score": 1,
          "player_name": "Franco Cristaldo"
        },
        {
          "time": 44,
          "type": 1,
          "position": 1,
          "player_id": "jw2r09hllpvrz84",
          "away_score": 1,
          "home_score": 2,
          "player_name": "Diego Costa"
        },
        {
          "time": 46,
          "type": 3,
          "position": 2,
          "player_id": "dj2ryoh2y6nq1zp",
          "player_name": "Jean Carlos"
        },
        {
          "time": 48,
          "type": 3,
          "position": 1,
          "player_id": "x7lm7php20nm2wd",
          "player_name": "Mathias Villasanti"
        },
        {
          "time": 45,
          "type": 11,
          "position": 0
        },
        {
          "time": 46,
          "type": 9,
          "position": 2,
          "in_player_id": "318q66h4zwn3qo9",
          "out_player_id": "l7oqdeh4v7kdr51",
          "in_player_name": "Rildo Goncalves de Amorin Filho",
          "out_player_name": "Edson Guilherme Mendes dos Santos"
        },
        {
          "time": 52,
          "type": 3,
          "position": 1,
          "player_id": "318q66hjd89qo9j",
          "player_name": "Caíque"
        },
        {
          "time": 54,
          "type": 3,
          "position": 2,
          "player_id": "4wyrn4hdl4vpq86",
          "player_name": "João Lucas"
        },
        {
          "time": 71,
          "type": 9,
          "position": 2,
          "in_player_id": "jw2r09hpx7prz84",
          "out_player_id": "zp5rzghpy27zq82",
          "in_player_name": "Nenê",
          "out_player_name": "Lucas Henrique Barbosa"
        },
        {
          "time": 72,
          "type": 9,
          "position": 2,
          "in_player_id": "dn1m1gh3120zmoe",
          "out_player_id": "k82rekhyy0yrepz",
          "in_player_name": "Luiz Gustavo da Silva Machado Duarte",
          "out_player_name": "Jadson Alves dos Santos"
        },
        {
          "time": 74,
          "type": 9,
          "position": 1,
          "in_player_id": "n54qllh8lyg2qvy",
          "out_player_id": "1l4rjnhzvgwm7vx",
          "in_player_name": "Queiroz du",
          "out_player_name": "Franco Cristaldo"
        },
        {
          "time": 74,
          "type": 9,
          "position": 1,
          "in_player_id": "dn1m1ghoxkkmoep",
          "out_player_id": "4jwq2ghv6zdpm0v",
          "in_player_name": "Douglas Moreira Fagundes",
          "out_player_name": "Pepê"
        },
        {
          "time": 75,
          "type": 3,
          "position": 2,
          "player_id": "l5ergph3jgor8k0",
          "player_name": "Gilberto"
        },
        {
          "time": 80,
          "type": 9,
          "position": 1,
          "in_player_id": "4jwq2ghx06km0ve",
          "out_player_id": "k82rekh31jnkrep",
          "in_player_name": "Yeferson Soteldo",
          "out_player_name": "nunes gustavo"
        },
        {
          "time": 80,
          "type": 9,
          "position": 1,
          "in_player_id": "1l4rjnhkeey2m7v",
          "out_player_id": "pxwrxlh9o66ryk0",
          "in_player_name": "Fernandes nathan",
          "out_player_name": "Cristian Pavón"
        },
        {
          "time": 80,
          "type": 9,
          "position": 2,
          "in_player_id": "zp5rzghp2zw0q82",
          "out_player_id": "dj2ryoh2y6nq1zp",
          "in_player_name": "Erick Samuel Corrêa Farias",
          "out_player_name": "Jean Carlos"
        },
        {
          "time": 82,
          "type": 3,
          "position": 2,
          "player_id": "jw2r09hw1987rz8",
          "player_name": "goncalves caique"
        },
        {
          "time": 84,
          "type": 9,
          "position": 2,
          "in_player_id": "jw2r09hxdl7xrz8",
          "out_player_id": "4wyrn4hdl4vpq86",
          "in_player_name": "Kleiton·Pego Duarte",
          "out_player_name": "João Lucas"
        },
        {
          "time": 87,
          "type": 1,
          "position": 1,
          "player_id": "1l4rjnhkeey2m7v",
          "away_score": 1,
          "home_score": 3,
          "player_name": "Fernandes nathan"
        },
        {
          "time": 90,
          "type": 3,
          "position": 2,
          "player_id": "vjxm8gh2271r6od",
          "player_name": "Ze Marcos"
        },
        {
          "time": 90,
          "type": 9,
          "position": 1,
          "in_player_id": "dn1m1gh8100jmoe",
          "out_player_id": "jw2r09hllpvrz84",
          "in_player_name": "pedro joao",
          "out_player_name": "Diego Costa"
        },
        {
          "time": 95,
          "type": 3,
          "position": 1,
          "player_id": "4jwq2ghx06km0ve",
          "player_name": "Yeferson Soteldo"
        },
        {
          "time": 90,
          "type": 12,
          "position": 0
        }
      ]
    },
    "6ypq3nh3gv6ymd7": {
      "id": "6ypq3nh3gv6ymd7",
      "home_team_id": "gpxwrxlhoe0ryk0",
      "away_team_id": "l965mkyhxxxr1ge",
      "start_timestamp": 1710702000,
      "status_id": 8,
      "sport_event_status": {
        "status_id": 8,
        "away_score": {
          "corners": 6,
          "red_card": 0,
          "yellow_card": 2,
          "penalty_score": 0,
          "regular_score": 0,
          "overTime_score": 0,
          "half_time_score": 0
        },
        "home_score": {
          "corners": 2,
          "red_card": 0,
          "yellow_card": 3,
          "penalty_score": 0,
          "regular_score": 0,
          "overTime_score": 0,
          "half_time_score": 0
        }
      },
      "related_id": "",
      "incidents": [
        {
          "time": 8,
          "type": 3,
          "position": 1,
          "player_id": "zp5rzghpy27zq82",
          "player_name": "Lucas Henrique Barbosa"
        },
        {
          "time": 15,
          "type": 3,
          "position": 2,
          "player_id": "l965mkyhpvdr1ge",
          "player_name": "Charles Aránguiz"
        },
        {
          "time": 23,
          "type": 3,
          "position": 1,
          "player_id": "23xmvkhden7qg8n",
          "player_name": "Alan Luciano Ruschel"
        },
        {
          "time": 41,
          "type": 3,
          "position": 1,
          "player_id": "l7oqdeh4v7kdr51",
          "player_name": "Edson Guilherme Mendes dos Santos"
        },
        {
          "time": 45,
          "type": 11,
          "position": 0
        },
        {
          "time": 50,
          "type": 9,
          "position": 2,
          "in_player_id": "dn1m1ghn8eemoep",
          "out_player_id": "l7oqdehl12v2r51",
          "in_player_name": "Lucas Alario",
          "out_player_name": "valencia enner"
        },
        {
          "time": 68,
          "type": 9,
          "position": 2,
          "in_player_id": "zp5rzghz6ly8q82",
          "out_player_id": "l965mkyhpvdr1ge",
          "in_player_name": "Romulo",
          "out_player_name": "Charles Aránguiz"
        },
        {
          "time": 68,
          "type": 9,
          "position": 2,
          "in_player_id": "k82rekhyw008rep",
          "out_player_id": "x7lm7ph9pno7m2w",
          "in_player_name": "Bruno Gomes",
          "out_player_name": "henrique bruno"
        },
        {
          "time": 69,
          "type": 9,
          "position": 1,
          "in_player_id": "jw2r09hpx7prz84",
          "out_player_id": "l7oqdeh4v7kdr51",
          "in_player_name": "Nenê",
          "out_player_name": "Edson Guilherme Mendes dos Santos"
        },
        {
          "time": 75,
          "type": 3,
          "position": 2,
          "player_id": "dn1m1ghn8eemoep",
          "player_name": "Lucas Alario"
        },
        {
          "time": 84,
          "type": 9,
          "position": 1,
          "in_player_id": "k82rekhy4n6prep",
          "out_player_id": "4wyrn4hdl4vpq86",
          "in_player_name": "Sam rodrigo",
          "out_player_name": "João Lucas"
        },
        {
          "time": 84,
          "type": 9,
          "position": 1,
          "in_player_id": "318q66h4zwn3qo9",
          "out_player_id": "zp5rzghpy27zq82",
          "in_player_name": "Rildo Goncalves de Amorin Filho",
          "out_player_name": "Lucas Henrique Barbosa"
        },
        {
          "time": 84,
          "type": 9,
          "position": 1,
          "in_player_id": "1l4rjnhx0x7om7v",
          "out_player_id": "dj2ryoh2y6nq1zp",
          "in_player_name": "Ruan Pereira Duarte",
          "out_player_name": "Jean Carlos"
        },
        {
          "time": 85,
          "type": 9,
          "position": 2,
          "in_player_id": "l5ergphnpgpvr8k",
          "out_player_id": "2y8m4zhg8x6ql07",
          "in_player_name": "ribeiro wesley",
          "out_player_name": "Wanderson"
        },
        {
          "time": 85,
          "type": 9,
          "position": 2,
          "in_player_id": "k82rekho2d8erep",
          "out_player_id": "n54qllhek83qvy9",
          "in_player_name": "Lucca",
          "out_player_name": "Alan Patrick"
        },
        {
          "time": 96,
          "type": 9,
          "position": 1,
          "in_player_id": "ednm9whge2p9ryo",
          "out_player_id": "l5ergph3jgor8k0",
          "in_player_name": "pinna rafael",
          "out_player_name": "Gilberto"
        },
        {
          "time": 90,
          "type": 12,
          "position": 0
        }
      ]
    },
    "8yomo4h391eoq0j": {
      "id": "8yomo4h391eoq0j",
      "home_team_id": "23xmvkh3kj0qg8n",
      "away_team_id": "p4jwq2ghdd9m0ve",
      "start_timestamp": 1710617400,
      "status_id": 8,
      "sport_event_status": {
        "status_id": 8,
        "away_score": {
          "corners": 5,
          "red_card": 0,
          "yellow_card": 5,
          "penalty_score": 0,
          "regular_score": 2,
          "overTime_score": 0,
          "half_time_score": 1
        },
        "home_score": {
          "corners": 5,
          "red_card": 0,
          "yellow_card": 4,
          "penalty_score": 0,
          "regular_score": 1,
          "overTime_score": 0,
          "half_time_score": 0
        }
      },
      "related_id": "",
      "incidents": [
        {
          "time": 10,
          "type": 9,
          "position": 1,
          "in_player_id": "y0or5jh32o0nqwz",
          "out_player_id": "4wyrn4h46oknq86",
          "in_player_name": "Peu",
          "out_player_name": "Mandai dudu"
        },
        {
          "time": 11,
          "type": 3,
          "position": 1,
          "player_id": "k82rekh311zgrep",
          "player_name": "Marcelo"
        },
        {
          "time": 15,
          "type": 3,
          "position": 2,
          "player_id": "k82rekhy3zzrepz",
          "player_name": "Walter Kannemann"
        },
        {
          "time": 21,
          "type": 1,
          "position": 2,
          "player_id": "1l4rjnhzvgwm7vx",
          "away_score": 1,
          "home_score": 0,
          "player_name": "Franco Cristaldo"
        },
        {
          "time": 37,
          "type": 3,
          "position": 1,
          "player_id": "vjxm8ghpxnpxr6o",
          "player_name": "cezar"
        },
        {
          "time": 43,
          "type": 3,
          "position": 2,
          "player_id": "1l4rjnhzvgwm7vx",
          "player_name": "Franco Cristaldo"
        },
        {
          "time": 43,
          "type": 3,
          "position": 1,
          "player_id": "x7lm7ph0d1k6m2w",
          "player_name": "Elyeser"
        },
        {
          "time": 47,
          "type": 3,
          "position": 2,
          "player_id": "jw2r09hllpvrz84",
          "player_name": "Diego Costa"
        },
        {
          "time": 45,
          "type": 11,
          "position": 0
        },
        {
          "time": 54,
          "type": 9,
          "position": 1,
          "in_player_id": "l7oqdeh4kpvpr51",
          "out_player_id": "23xmvkhkn7v1qg8",
          "in_player_name": "Robinho",
          "out_player_name": "Martins emerson"
        },
        {
          "time": 59,
          "type": 3,
          "position": 2,
          "player_id": "x7lm7php20nm2wd",
          "player_name": "Mathias Villasanti"
        },
        {
          "time": 68,
          "type": 8,
          "position": 2,
          "player_id": "jw2r09hllpvrz84",
          "away_score": 2,
          "home_score": 0,
          "player_name": "Diego Costa"
        },
        {
          "time": 71,
          "type": 9,
          "position": 2,
          "in_player_id": "1l4rjnhkeey2m7v",
          "out_player_id": "pxwrxlh9o66ryk0",
          "in_player_name": "Fernandes nathan",
          "out_player_name": "Cristian Pavón"
        },
        {
          "time": 71,
          "type": 9,
          "position": 2,
          "in_player_id": "dn1m1ghoxkkmoep",
          "out_player_id": "4jwq2ghv6zdpm0v",
          "in_player_name": "Douglas Moreira Fagundes",
          "out_player_name": "Pepê"
        },
        {
          "time": 71,
          "type": 9,
          "position": 2,
          "in_player_id": "n54qllh8lyg2qvy",
          "out_player_id": "1l4rjnhzvgwm7vx",
          "in_player_name": "Queiroz du",
          "out_player_name": "Franco Cristaldo"
        },
        {
          "time": 76,
          "type": 17,
          "position": 1,
          "player_id": "n54qllh8lyg2qvy",
          "away_score": 2,
          "home_score": 1,
          "player_name": "Queiroz du"
        },
        {
          "time": 81,
          "type": 9,
          "position": 2,
          "in_player_id": "dn1m1gh8100jmoe",
          "out_player_id": "jw2r09hllpvrz84",
          "in_player_name": "pedro joao",
          "out_player_name": "Diego Costa"
        },
        {
          "time": 82,
          "type": 3,
          "position": 2,
          "player_id": "l7oqdeh4ee4pr51",
          "player_name": "Mayk·Van Van"
        },
        {
          "time": 84,
          "type": 9,
          "position": 2,
          "in_player_id": "pxwrxlhzv7o9ryk",
          "out_player_id": "k82rekh31jnkrep",
          "in_player_name": "ely rodrigo",
          "out_player_name": "nunes gustavo"
        },
        {
          "time": 87,
          "type": 9,
          "position": 1,
          "in_player_id": "l5ergphnpy95r8k",
          "out_player_id": "zp5rzgh1vddq82w",
          "in_player_name": "galvan augusto",
          "out_player_name": "Vitor Feijão"
        },
        {
          "time": 88,
          "type": 9,
          "position": 1,
          "in_player_id": "8yomo4hvd54wq0j",
          "out_player_id": "x7lm7ph0d1k6m2w",
          "in_player_name": "Cuiaba pedro",
          "out_player_name": "Elyeser"
        },
        {
          "time": 88,
          "type": 9,
          "position": 1,
          "in_player_id": "4wyrn4hv92k9q86",
          "out_player_id": "zp5rzghp6wk1q82",
          "in_player_name": "vinicius joel",
          "out_player_name": "Alvaro"
        },
        {
          "time": 96,
          "type": 3,
          "position": 1,
          "player_id": "8yomo4hvd54wq0j",
          "player_name": "Cuiaba pedro"
        },
        {
          "time": 90,
          "type": 12,
          "position": 0
        }
      ]
    },
    "dj2ryoh15g42q1z": {
      "id": "dj2ryoh15g42q1z",
      "home_team_id": "l965mkyhxxxr1ge",
      "away_team_id": "jw2r09hx362rz84",
      "start_timestamp": 1710012600,
      "status_id": 8,
      "sport_event_status": {
        "status_id": 8,
        "away_score": {
          "corners": 5,
          "red_card": 0,
          "yellow_card": 0,
          "penalty_score": 0,
          "regular_score": 0,
          "overTime_score": 0,
          "half_time_score": 0
        },
        "home_score": {
          "corners": 3,
          "red_card": 0,
          "yellow_card": 1,
          "penalty_score": 0,
          "regular_score": 3,
          "overTime_score": 0,
          "half_time_score": 2
        }
      },
      "related_id": "",
      "incidents": [
        {
          "time": 5,
          "type": 1,
          "position": 1,
          "player_id": "l7oqdehl12v2r51",
          "away_score": 0,
          "home_score": 1,
          "player_name": "valencia enner"
        },
        {
          "time": 17,
          "type": 1,
          "position": 1,
          "player_id": "zp5rzghz5el9q82",
          "away_score": 0,
          "home_score": 2,
          "player_name": "Igor Gomes"
        },
        {
          "time": 32,
          "type": 9,
          "position": 2,
          "in_player_id": "vjxm8gh8lyddr6o",
          "out_player_id": "8yomo4h0zgyxq0j",
          "in_player_name": "Ramires",
          "out_player_name": "luquinha"
        },
        {
          "time": 34,
          "type": 9,
          "position": 1,
          "in_player_id": "dj2ryohg7vo5q1z",
          "out_player_id": "zp5rzghz5el9q82",
          "in_player_name": "Robert Renan Alves Barbosa",
          "out_player_name": "Igor Gomes"
        },
        {
          "time": 45,
          "type": 11,
          "position": 0
        },
        {
          "time": 46,
          "type": 9,
          "position": 2,
          "in_player_id": "8yomo4hvv0lzq0j",
          "out_player_id": "318q66h44kvnqo9",
          "in_player_name": "Baiano felipe",
          "out_player_name": "Hulk lucas"
        },
        {
          "time": 46,
          "type": 9,
          "position": 2,
          "in_player_id": "6ypq3nhl1ejvmd7",
          "out_player_id": "dj2ryohn24zxq1z",
          "in_player_name": "morbeck gabriel",
          "out_player_name": "pereira gabriel"
        },
        {
          "time": 47,
          "type": 3,
          "position": 1,
          "player_id": "l965mkyhpvdr1ge",
          "player_name": "Charles Aránguiz"
        },
        {
          "time": 61,
          "type": 9,
          "position": 2,
          "in_player_id": "8yomo4h0zxd3q0j",
          "out_player_id": "zp5rzghpg2nvq82",
          "in_player_name": "sodre diogo",
          "out_player_name": "Pian dal guilherme"
        },
        {
          "time": 67,
          "type": 9,
          "position": 1,
          "in_player_id": "x7lm7ph0l66m2wd",
          "out_player_id": "2y8m4zhg8x6ql07",
          "in_player_name": "Hyoran",
          "out_player_name": "Wanderson"
        },
        {
          "time": 67,
          "type": 9,
          "position": 1,
          "in_player_id": "k82rekhyw008rep",
          "out_player_id": "l965mkyhpvdr1ge",
          "in_player_name": "Bruno Gomes",
          "out_player_name": "Charles Aránguiz"
        },
        {
          "time": 67,
          "type": 9,
          "position": 1,
          "in_player_id": "dn1m1ghn8eemoep",
          "out_player_id": "l7oqdehl12v2r51",
          "in_player_name": "Lucas Alario",
          "out_player_name": "valencia enner"
        },
        {
          "time": 68,
          "type": 9,
          "position": 2,
          "in_player_id": "dn1m1gh3w885moe",
          "out_player_id": "dn1m1ghn0xy2moe",
          "in_player_name": "Peixoto vini",
          "out_player_name": "Benjamín Borasi"
        },
        {
          "time": 80,
          "type": 9,
          "position": 1,
          "in_player_id": "k82rekho2d8erep",
          "out_player_id": "n54qllhek83qvy9",
          "in_player_name": "Lucca",
          "out_player_name": "Alan Patrick"
        },
        {
          "time": 84,
          "type": 1,
          "position": 1,
          "player_id": "8yomo4h2gkkkq0j",
          "away_score": 0,
          "home_score": 3,
          "player_name": "Mauricio Magalhães Prado"
        }
      ]
    },
    "jw2r09h27j9jrz8": {
      "id": "jw2r09h27j9jrz8",
      "home_team_id": "965mkyh49yer1ge",
      "away_team_id": "gpxwrxlhoe0ryk0",
      "start_timestamp": 1710023400,
      "status_id": 8,
      "sport_event_status": {
        "status_id": 8,
        "away_score": {
          "corners": 4,
          "red_card": 0,
          "yellow_card": 3,
          "penalty_score": 0,
          "regular_score": 4,
          "overTime_score": 0,
          "half_time_score": 0
        },
        "home_score": {
          "corners": 4,
          "red_card": 0,
          "yellow_card": 2,
          "penalty_score": 0,
          "regular_score": 0,
          "overTime_score": 0,
          "half_time_score": 0
        }
      },
      "related_id": "",
      "incidents": [
        {
          "time": 45,
          "type": 11,
          "position": 0
        },
        {
          "time": 46,
          "type": 9,
          "position": 2,
          "in_player_id": "l5ergphnpyg5r8k",
          "out_player_id": "vjxm8gh2271r6od",
          "in_player_name": "freitas lucas",
          "out_player_name": "Ze Marcos"
        },
        {
          "time": 47,
          "type": 1,
          "position": 2,
          "player_id": "l5ergph3jgor8k0",
          "away_score": 1,
          "home_score": 0,
          "player_name": "Gilberto"
        },
        {
          "time": 52,
          "type": 3,
          "position": 2,
          "player_id": "dj2ryoh2y6nq1zp",
          "player_name": "Jean Carlos"
        },
        {
          "time": 61,
          "type": 3,
          "position": 2,
          "player_id": "jw2r09hw1987rz8",
          "player_name": "goncalves caique"
        },
        {
          "time": 61,
          "type": 9,
          "position": 1,
          "in_player_id": "4jwq2gh710vwm0v",
          "out_player_id": "dj2ryohglvwvq1z",
          "in_player_name": "Hugo",
          "out_player_name": "Micael"
        },
        {
          "time": 63,
          "type": 9,
          "position": 2,
          "in_player_id": "k82rekhy4n6prep",
          "out_player_id": "jw2r09hw1987rz8",
          "in_player_name": "Sam rodrigo",
          "out_player_name": "goncalves caique"
        },
        {
          "time": 65,
          "type": 1,
          "position": 2,
          "player_id": "dj2ryoh2y6nq1zp",
          "away_score": 2,
          "home_score": 0,
          "player_name": "Jean Carlos"
        },
        {
          "time": 67,
          "type": 1,
          "position": 2,
          "away_score": 3,
          "home_score": 0
        }
      ]
    },
    "l5ergphw2eyvr8k": {
      "id": "l5ergphw2eyvr8k",
      "home_team_id": "p4jwq2ghdd9m0ve",
      "away_team_id": "vjxm8ghg9x6r6od",
      "start_timestamp": 1710106200,
      "status_id": 8,
      "sport_event_status": {
        "status_id": 8,
        "away_score": {
          "corners": 0,
          "red_card": 1,
          "yellow_card": 1,
          "penalty_score": 0,
          "regular_score": 0,
          "overTime_score": 0,
          "half_time_score": 0
        },
        "home_score": {
          "corners": 5,
          "red_card": 0,
          "yellow_card": 2,
          "penalty_score": 0,
          "regular_score": 2,
          "overTime_score": 0,
          "half_time_score": 1
        }
      },
      "related_id": "",
      "incidents": [
        {
          "time": 45,
          "type": 19,
          "position": 0
        },
        {
          "time": 46,
          "type": 1,
          "position": 1,
          "player_id": "1l4rjnhzvgwm7vx",
          "assist1_id": "l7oqdeh4ee4pr51",
          "away_score": 0,
          "home_score": 1,
          "player_name": "Franco Cristaldo",
          "assist1_name": "Mayk·Van Van"
        },
        {
          "time": 51,
          "type": 11,
          "position": 0
        },
        {
          "time": 45,
          "type": 9,
          "position": 2,
          "reason_type": 4,
          "in_player_id": "318q66h452x0qo9",
          "out_player_id": "zp5rzghpw357q82",
          "in_player_name": "Vinicius charopem",
          "out_player_name": "Dionatan Machado de Oliveira"
        },
        {
          "time": 57,
          "type": 9,
          "position": 2,
          "reason_type": 4,
          "in_player_id": "l7oqdeh0j38kr51",
          "out_player_id": "l5ergphvgjp3r8k",
          "in_player_name": "Robson Santos do Carmo Junior",
          "out_player_name": "João Pedro Bardales da Silva"
        },
        {
          "time": 59,
          "type": 3,
          "position": 2,
          "player_id": "l5ergph2p5vr8k0",
          "player_name": "Pedro Santos",
          "reason_type": 1
        },
        {
          "time": 63,
          "type": 3,
          "position": 1,
          "player_id": "4jwq2ghv6zdpm0v",
          "player_name": "Pepê",
          "reason_type": 1
        },
        {
          "time": 65,
          "type": 9,
          "position": 1,
          "reason_type": 4,
          "in_player_id": "8yomo4hv5o96q0j",
          "out_player_id": "4jwq2ghv6zdpm0v",
          "in_player_name": "Eduardo Santos Queiroz",
          "out_player_name": "Pepê"
        },
        {
          "time": 66,
          "type": 9,
          "position": 2,
          "reason_type": 4,
          "in_player_id": "zp5rzghx2glyq82",
          "out_player_id": "zp5rzghzo3nkq82",
          "in_player_name": "Yander",
          "out_player_name": "Gabriel Biteco"
        },
        {
          "time": 66,
          "type": 9,
          "position": 2,
          "reason_type": 4,
          "in_player_id": "l7oqdeh45geer51",
          "out_player_id": "l5ergph2p5vr8k0",
          "in_player_name": "Maicky Henrique Galastri Gomes",
          "out_player_name": "Pedro Santos"
        },
        {
          "time": 69,
          "type": 1,
          "position": 1,
          "player_id": "jw2r09hllpvrz84",
          "assist1_id": "8yomo4hv5o96q0j",
          "away_score": 0,
          "home_score": 2,
          "player_name": "Diego Costa",
          "assist1_name": "Eduardo Santos Queiroz"
        },
        {
          "time": 76,
          "type": 9,
          "position": 1,
          "reason_type": 4,
          "in_player_id": "l7oqdeh451l7r51",
          "out_player_id": "pxwrxlh9o66ryk0",
          "in_player_name": "André Henrique da Silva Martins",
          "out_player_name": "Cristian Pavón"
        },
        {
          "time": 76,
          "type": 9,
          "position": 1,
          "reason_type": 4,
          "in_player_id": "4jwq2gh74d32m0v",
          "out_player_id": "l7oqdeh4ee4pr51",
          "in_player_name": "Wesley·Da Costa Silva",
          "out_player_name": "Mayk·Van Van"
        },
        {
          "time": 76,
          "type": 9,
          "position": 1,
          "reason_type": 4,
          "in_player_id": "2y8m4zhj17eql07",
          "out_player_id": "jw2r09hllpvrz84",
          "in_player_name": "João Pedro",
          "out_player_name": "Diego Costa"
        },
        {
          "time": 83,
          "type": 4,
          "position": 2,
          "player_id": "23xmvkh4g657qg8",
          "player_name": "Bruno Reis",
          "reason_type": 9
        },
        {
          "time": 84,
          "type": 9,
          "position": 1,
          "reason_type": 4,
          "in_player_id": "dn1m1ghoxkkmoep",
          "out_player_id": "k82rekhy3zzrepz",
          "in_player_name": "Douglas Moreira Fagundes",
          "out_player_name": "Walter Kannemann"
        },
        {
          "time": 86,
          "type": 9,
          "position": 2,
          "reason_type": 4,
          "in_player_id": "jw2r09hx8dnerz8",
          "out_player_id": "318q66hnk7zqo9j",
          "in_player_name": "Jeferson Mesquita Lopes",
          "out_player_name": "Marcinho"
        },
        {
          "time": 90,
          "type": 3,
          "position": 1,
          "player_id": "8y39mp1h2ejmojx",
          "player_name": "Pedro Geromel",
          "reason_type": 1
        }
      ]
    },
    "l7oqdehod02lr51": {
      "id": "l7oqdehod02lr51",
      "home_team_id": "23xmvkh3kj0qg8n",
      "away_team_id": "ednm9whkod9ryox",
      "start_timestamp": 1709935200,
      "status_id": 8,
      "sport_event_status": {
        "status_id": 8,
        "away_score": {
          "corners": 8,
          "red_card": 0,
          "yellow_card": 6,
          "penalty_score": 0,
          "regular_score": 0,
          "overTime_score": 0,
          "half_time_score": 0
        },
        "home_score": {
          "corners": 5,
          "red_card": 1,
          "yellow_card": 2,
          "penalty_score": 0,
          "regular_score": 1,
          "overTime_score": 0,
          "half_time_score": 1
        }
      },
      "related_id": "",
      "incidents": [
        {
          "time": 4,
          "type": 1,
          "position": 1,
          "player_id": "zp5rzgh1vddq82w",
          "away_score": 0,
          "home_score": 1,
          "player_name": "Vitor Feijão"
        },
        {
          "time": 12,
          "type": 3,
          "position": 1,
          "player_id": "k82rekh311zgrep",
          "player_name": "Marcelo"
        },
        {
          "time": 14,
          "type": 3,
          "position": 2,
          "player_id": "x7lm7ph9pp00m2w",
          "player_name": "Calazans marcos"
        },
        {
          "time": 19,
          "type": 3,
          "position": 2,
          "player_id": "318q66h44526qo9",
          "player_name": "Itambe"
        },
        {
          "time": 41,
          "type": 9,
          "position": 2,
          "in_player_id": "6ypq3nhl4691md7",
          "out_player_id": "y39mp1hy7j1dmoj",
          "in_player_name": "cesar augusto",
          "out_player_name": "Nonato"
        },
        {
          "time": 45,
          "type": 11,
          "position": 0
        },
        {
          "time": 46,
          "type": 9,
          "position": 2,
          "in_player_id": "y39mp1hy2p7wmoj",
          "out_player_id": "318q66h44526qo9",
          "in_player_name": "Ariel",
          "out_player_name": "Itambe"
        },
        {
          "time": 60,
          "type": 4,
          "position": 1,
          "player_id": "dn1m1gh368yxmoe",
          "player_name": "Silva gabriel"
        },
        {
          "time": 62,
          "type": 9,
          "position": 1,
          "in_player_id": "zp5rzghp6wk1q82",
          "out_player_id": "jw2r09hw19o7rz8",
          "in_player_name": "Alvaro",
          "out_player_name": "lustosa david"
        },
        {
          "time": 68,
          "type": 9,
          "position": 2,
          "in_player_id": "zp5rzghx15j4q82",
          "out_player_id": "2y8m4zhz1xlwql0",
          "in_player_name": "marquinhos",
          "out_player_name": "samuel"
        },
        {
          "time": 68,
          "type": 9,
          "position": 1,
          "in_player_id": "l7oqdeh4kpvpr51",
          "out_player_id": "zp5rzgh1vddq82w",
          "in_player_name": "Robinho",
          "out_player_name": "Vitor Feijão"
        },
        {
          "time": 70,
          "type": 28,
          "position": 1,
          "player_id": "l7oqdeh4kpvpr51",
          "var_reason": 0,
          "var_result": 0,
          "player_name": "Robinho"
        },
        {
          "time": 78,
          "type": 3,
          "position": 2,
          "player_id": "2y8m4zh828l6ql0",
          "player_name": "Matheuzinho"
        },
        {
          "time": 80,
          "type": 3,
          "position": 2,
          "player_id": "y39mp1hy2p7wmoj",
          "player_name": "Ariel"
        }
      ]
    }
  }
}